Day_1/day1.sv
`timescale 1 ps / 1 ps

`define LOWER_BOUND 8'h30
`define UPPER_BOUND 8'h39

module day1 (
    input  logic clk,
    input  logic rst,

    // axis input
    input logic tvalid_rx,
    output logic tready_rx,
    input logic [7:0] tdata_rx,
    input logic tlast_rx,

    // axis output
    output logic tvalid_tx,
    input logic tready_tx,
    output logic [31:0] tdata_tx,
    output logic tlast_tx
);

typedef enum {FIRST_DIG_SEARCH, SECOND_DIG_SEARCH, DO_MAC, OUTPUT_RESULT} state_t;

// state machine register
state_t state;

// accumulator with the output value
logic [31:0] acc;

// digit registers
logic [3:0] first_dig;
logic [3:0] second_dig;

// convienient functions
logic is_number;
logic [7:0] num_shift;

assign is_number = (tdata_rx <= `UPPER_BOUND && tdata_rx >= `LOWER_BOUND);
assign num_shift = (tdata_rx - 8'h30);

always @(posedge clk) begin
  if(rst) begin
    state <= FIRST_DIG_SEARCH;
    acc <= '0;
    tready_rx <= 1'b0;
    first_dig <= 4'h0;
    second_dig <= 4'hF;

    tlast_tx <= 1'b0;
    tdata_tx <= '0;
    tvalid_tx <= 1'b0;
  end else begin
    case (state)
      FIRST_DIG_SEARCH: begin
        tready_rx <= 1'b1;
        if(tvalid_rx && is_number) begin
          first_dig <= num_shift[3:0];

          if(tlast_rx) begin
            state <= DO_MAC;
            tready_rx <= 1'b0;
          end
          else state <= SECOND_DIG_SEARCH;
        end
      end
      SECOND_DIG_SEARCH: begin
        tready_rx <= 1'b1;

        if(tvalid_rx && is_number) begin
          second_dig <= num_shift[3:0];
        end

        if(tlast_rx) begin
          tready_rx <= 1'b0;
          state <= DO_MAC;
        end
      end
      DO_MAC: begin
        // tready_rx <= 1'b0;

        if(second_dig == 4'hF) begin
          acc <= acc + (first_dig * 4'd10) + first_dig;
        end
        else acc <= acc + (first_dig * 4'd10) + second_dig;

        second_dig <= 4'hF;
        first_dig <= 4'h0;

        if(tready_tx) state <= OUTPUT_RESULT;
        else begin
          tready_rx <= 1'b1;
          state <= FIRST_DIG_SEARCH;
        end
      end
      OUTPUT_RESULT: begin
        tready_rx <= 1'b0;
        tvalid_tx <= 1'b1;
        tdata_tx <= acc;
        tlast_tx <= 1'b1;
      end
      default: state <= FIRST_DIG_SEARCH;
    endcase
  end
end



endmodule

Day_1/dut_tb.sv
`timescale 1 ps / 1 ps

`define MEM_LENGTH 21529
// `define MEM_LENGTH 48


module dut_tb
(
    input wire clk,
    input wire rst
);

logic [$clog2(`MEM_LENGTH)-1:0] ptr;
logic [7:0] mem0 [0:`MEM_LENGTH];
logic [31:0] result [7:0];

// into DUT
logic tvalid_rx;
logic tready_rx;
logic [7:0] tdata_rx;
logic tlast_rx;

// out of DUT
logic tvalid_tx;
logic tready_tx;
logic [31:0] tdata_tx;
logic tlast_tx;

typedef enum {WRITE, READ} state_t;

state_t state;

initial begin
  $readmemh("day1.mem", mem0);
end

always @(negedge clk) begin
  if(rst) begin
    ptr <= '0;
    tvalid_rx <= 1'b0;
    tready_tx <= 1'b0;
    tdata_rx <= '0;
    tlast_rx <= 1'b0;
  end else begin
    case(state)
      WRITE: begin
        if(ptr == `MEM_LENGTH) begin
            state <= READ;
            tvalid_rx <= 1'b0;
            tready_tx <= 1'b1;
        end else begin
            tvalid_rx <= 1'b1;
            tdata_rx <= mem0[ptr];

            if(mem0[ptr+1] == 8'hFF) tlast_rx <= 1'b1;
            else tlast_rx <= 1'b0;

            if(tready_rx) begin
              if(mem0[ptr+1] == 8'hFF) ptr <= ptr + 2;
              else ptr <= ptr + 1;
            end
        end
      end
      READ: begin
        tready_tx <= 1'b1;

        result[0] <= tdata_tx;

        if(tvalid_tx) ptr <= '0;

        if(ptr == '0)
            $finish;
      end
      default: begin
        state <= WRITE;
      end
    endcase
  end
end

day1 dut (
  .clk(clk),
  .rst(rst),

  // axis input
  .tvalid_rx(tvalid_rx),
  .tready_rx(tready_rx),
  .tdata_rx(tdata_rx),
  .tlast_rx(tlast_rx),

  // axis output
  .tvalid_tx(tvalid_tx),
  .tready_tx(tready_tx),
  .tdata_tx(tdata_tx),
  .tlast_tx(tlast_tx)
);

  final begin
    $writememb("result.mem", result);
  end

endmodule

Day_1/sim.vcd
$version Generated by VerilatedVcd $end
$timescale 1ps $end

 $scope module TOP $end
  $var wire  1 ; clk $end
  $var wire  1 < rst $end
  $scope module dut_tb $end
   $var wire  1 ; clk $end
   $var wire 15 # ptr [14:0] $end
   $var wire 32 $ result[0] [31:0] $end
   $var wire 32 % result[1] [31:0] $end
   $var wire 32 & result[2] [31:0] $end
   $var wire 32 ' result[3] [31:0] $end
   $var wire 32 ( result[4] [31:0] $end
   $var wire 32 ) result[5] [31:0] $end
   $var wire 32 * result[6] [31:0] $end
   $var wire 32 + result[7] [31:0] $end
   $var wire  1 < rst $end
   $var wire 32 0 state [31:0] $end
   $var wire  8 - tdata_rx [7:0] $end
   $var wire 32 5 tdata_tx [31:0] $end
   $var wire  1 . tlast_rx $end
   $var wire  1 6 tlast_tx $end
   $var wire  1 3 tready_rx $end
   $var wire  1 / tready_tx $end
   $var wire  1 , tvalid_rx $end
   $var wire  1 4 tvalid_tx $end
   $scope module dut $end
    $var wire 32 8 acc [31:0] $end
    $var wire  1 ; clk $end
    $var wire  4 9 first_dig [3:0] $end
    $var wire  1 1 is_number $end
    $var wire  8 2 num_shift [7:0] $end
    $var wire  1 < rst $end
    $var wire  4 : second_dig [3:0] $end
    $var wire 32 7 state [31:0] $end
    $var wire  8 - tdata_rx [7:0] $end
    $var wire 32 5 tdata_tx [31:0] $end
    $var wire  1 . tlast_rx $end
    $var wire  1 6 tlast_tx $end
    $var wire  1 3 tready_rx $end
    $var wire  1 / tready_tx $end
    $var wire  1 , tvalid_rx $end
    $var wire  1 4 tvalid_tx $end
   $upscope $end
  $upscope $end
 $upscope $end
$enddefinitions $end


#0
b000000000000000 #
b00000000000000000000000000000000 $
b00000000000000000000000000000000 %
b00000000000000000000000000000000 &
b00000000000000000000000000000000 '
b00000000000000000000000000000000 (
b00000000000000000000000000000000 )
b00000000000000000000000000000000 *
b00000000000000000000000000000000 +
0,
b00000000 -
0.
0/
b00000000000000000000000000000000 0
01
b11010000 2
03
04
b00000000000000000000000000000000 5
06
b00000000000000000000000000000000 7
b00000000000000000000000000000000 8
b0000 9
b0000 :
0;
1<
#1
b1111 :
1;
#2
0;
#3
1;
#4
0;
#5
13
1;
0<
#6
b000000000000001 #
1,
b00110100 -
11
b00000100 2
0;
#7
b00000000000000000000000000000001 7
b0100 9
1;
#8
b000000000000010 #
b00110110 -
b00000110 2
0;
#9
b0110 :
1;
#10
b000000000000011 #
b01110100 -
01
b01000100 2
0;
#11
1;
#12
b000000000000100 #
b01101000 -
b00111000 2
0;
#13
1;
#14
b000000000000101 #
b01110010 -
b01000010 2
0;
#15
1;
#16
b000000000000110 #
b01100101 -
b00110101 2
0;
#17
1;
#18
b000000000000111 #
0;
#19
1;
#20
b000000000001000 #
b01110110 -
b01000110 2
0;
#21
1;
#22
b000000000001001 #
b01110001 -
b01000001 2
0;
#23
1;
#24
b000000000001010 #
b01110011 -
b01000011 2
0;
#25
1;
#26
b000000000001011 #
b00111000 -
11
b00001000 2
0;
#27
b1000 :
1;
#28
b000000000001100 #
b00110001 -
b00000001 2
0;
#29
b0001 :
1;
#30
b000000000001101 #
0;
#31
1;
#32
b000000000001111 #
b00110100 -
1.
b00000100 2
0;
#33
03
b00000000000000000000000000000010 7
b0100 :
1;
#34
b01110100 -
0.
01
b01000100 2
0;
#35
13
b00000000000000000000000000000000 7
b00000000000000000000000000101100 8
b0000 9
b1111 :
1;
#36
b000000000010000 #
0;
#37
1;
#38
b000000000010001 #
b01101000 -
b00111000 2
0;
#39
1;
#40
b000000000010010 #
b01110010 -
b01000010 2
0;
#41
1;
#42
b000000000010011 #
b01100101 -
b00110101 2
0;
#43
1;
#44
b000000000010100 #
0;
#45
1;
#46
b000000000010101 #
b01110100 -
b01000100 2
0;
#47
1;
#48
b000000000010110 #
b01110111 -
b01000111 2
0;
#49
1;
#50
b000000000010111 #
b01101111 -
b00111111 2
0;
#51
1;
#52
b000000000011000 #
0;
#53
1;
#54
b000000000011001 #
b01101110 -
b00111110 2
0;
#55
1;
#56
b000000000011010 #
b01100101 -
b00110101 2
0;
#57
1;
#58
b000000000011011 #
b01111010 -
b01001010 2
0;
#59
1;
#60
b000000000011100 #
b00110001 -
11
b00000001 2
0;
#61
b00000000000000000000000000000001 7
b0001 9
1;
#62
b000000000011101 #
b01100111 -
01
b00110111 2
0;
#63
1;
#64
b000000000011110 #
b01110100 -
b01000100 2
0;
#65
1;
#66
b000000000011111 #
b01110010 -
b01000010 2
0;
#67
1;
#68
b000000000100001 #
b01100100 -
1.
b00110100 2
0;
#69
03
b00000000000000000000000000000010 7
1;
#70
b00110110 -
0.
11
b00000110 2
0;
#71
13
b00000000000000000000000000000000 7
b00000000000000000000000000110111 8
b0000 9
1;
#72
b000000000100010 #
0;
#73
b00000000000000000000000000000001 7
b0110 9
1;
#74
b000000000100011 #
b01100110 -
01
b00110110 2
0;
#75
1;
#76
b000000000100100 #
0;
#77
1;
#78
b000000000100101 #
b01111000 -
b01001000 2
0;
#79
1;
#80
b000000000100110 #
b01100010 -
b00110010 2
0;
#81
1;
#82
b000000000100111 #
b01110100 -
b01000100 2
0;
#83
1;
#84
b000000000101000 #
b01100110 -
b00110110 2
0;
#85
1;
#86
b000000000101010 #
1.
0;
#87
03
b00000000000000000000000000000010 7
1;
#88
b00110111 -
0.
11
b00000111 2
0;
#89
13
b00000000000000000000000000000000 7
b00000000000000000000000001111001 8
b0000 9
1;
#90
b000000000101011 #
0;
#91
b00000000000000000000000000000001 7
b0111 9
1;
#92
b000000000101100 #
b00110110 -
b00000110 2
0;
#93
b0110 :
1;
#94
b000000000101101 #
b00111001 -
b00001001 2
0;
#95
b1001 :
1;
#96
b000000000101110 #
b01110100 -
01
b01000100 2
0;
#97
1;
#98
b000000000101111 #
b01110111 -
b01000111 2
0;
#99
1;
#100
b000000000110000 #
b01101111 -
b00111111 2
0;
#101
1;
#102
b000000000110001 #
b01110100 -
b01000100 2
0;
#103
1;
#104
b000000000110010 #
b01110111 -
b01000111 2
0;
#105
1;
#106
b000000000110011 #
b01101111 -
b00111111 2
0;
#107
1;
#108
b000000000110100 #
b00110110 -
11
b00000110 2
0;
#109
b0110 :
1;
#110
b000000000110101 #
b01110010 -
01
b01000010 2
0;
#111
1;
#112
b000000000110110 #
b01110110 -
b01000110 2
0;
#113
1;
#114
b000000000111000 #
b00111001 -
1.
11
b00001001 2
0;
#115
03
b00000000000000000000000000000010 7
b1001 :
1;
#116
b01100111 -
0.
01
b00110111 2
0;
#117
13
b00000000000000000000000000000000 7
b00000000000000000000000011001000 8
b0000 9
b1111 :
1;
#118
b000000000111001 #
0;
#119
1;
#120
b000000000111010 #
b01101010 -
b00111010 2
0;
#121
1;
#122
b000000000111011 #
b01110010 -
b01000010 2
0;
#123
1;
#124
b000000000111100 #
b01100011 -
b00110011 2
0;
#125
1;
#126
b000000000111101 #
b01101010 -
b00111010 2
0;
#127
1;
#128
b000000000111110 #
b01110010 -
b01000010 2
0;
#129
1;
#130
b000000000111111 #
b01101011 -
b00111011 2
0;
#131
1;
#132
b000000001000000 #
b01110110 -
b01000110 2
0;
#133
1;
#134
b000000001000001 #
b01100111 -
b00110111 2
0;
#135
1;
#136
b000000001000010 #
b01101000 -
b00111000 2
0;
#137
1;
#138
b000000001000011 #
b01110100 -
b01000100 2
0;
#139
1;
#140
b000000001000100 #
b01101000 -
b00111000 2
0;
#141
1;
#142
b000000001000101 #
b01110010 -
b01000010 2
0;
#143
1;
#144
b000000001000110 #
b01100101 -
b00110101 2
0;
#145
1;
#146
b000000001000111 #
0;
#147
1;
#148
b000000001001000 #
b01100111 -
b00110111 2
0;
#149
1;
#150
b000000001001001 #
b01110001 -
b01000001 2
0;
#151
1;
#152
b000000001001010 #
0;
#153
1;
#154
b000000001001011 #
b01110010 -
b01000010 2
0;
#155
1;
#156
b000000001001100 #
b01100111 -
b00110111 2
0;
#157
1;
#158
b000000001001101 #
b00111000 -
11
b00001000 2
0;
#159
b00000000000000000000000000000001 7
b1000 9
1;
#160
b000000001001110 #
b00110010 -
b00000010 2
0;
#161
b0010 :
1;
#162
b000000001001111 #
b01110001 -
01
b01000001 2
0;
#163
1;
#164
b000000001010000 #
b01100010 -
b00110010 2
0;
#165
1;
#166
b000000001010001 #
b01100011 -
b00110011 2
0;
#167
1;
#168
b000000001010011 #
b01110100 -
1.
b01000100 2
0;
#169
03
b00000000000000000000000000000010 7
1;
#170
b01111010 -
0.
b01001010 2
0;
#171
13
b00000000000000000000000000000000 7
b00000000000000000000000100011010 8
b0000 9
b1111 :
1;
#172
b000000001010100 #
0;
#173
1;
#174
b000000001010101 #
b01101011 -
b00111011 2
0;
#175
1;
#176
b000000001010110 #
b01111000 -
b01001000 2
0;
#177
1;
#178
b000000001010111 #
b01101010 -
b00111010 2
0;
#179
1;
#180
b000000001011000 #
b01101000 -
b00111000 2
0;
#181
1;
#182
b000000001011001 #
b01100111 -
b00110111 2
0;
#183
1;
#184
b000000001011010 #
b01110000 -
b01000000 2
0;
#185
1;
#186
b000000001011011 #
b01110010 -
b01000010 2
0;
#187
1;
#188
b000000001011100 #
b01110100 -
b01000100 2
0;
#189
1;
#190
b000000001011101 #
b01110010 -
b01000010 2
0;
#191
1;
#192
b000000001011110 #
b01101100 -
b00111100 2
0;
#193
1;
#194
b000000001011111 #
b01100011 -
b00110011 2
0;
#195
1;
#196
b000000001100000 #
b01100110 -
b00110110 2
0;
#197
1;
#198
b000000001100001 #
b01100101 -
b00110101 2
0;
#199
1;
#200
b000000001100010 #
b01101001 -
b00111001 2
0;
#201
1;
#202
b000000001100011 #
b01100111 -
b00110111 2
0;
#203
1;
#204
b000000001100100 #
b01101000 -
b00111000 2
0;
#205
1;
#206
b000000001100101 #
b01110100 -
b01000100 2
0;
#207
1;
#208
b000000001100110 #
b00110111 -
11
b00000111 2
0;
#209
b00000000000000000000000000000001 7
b0111 9
1;
#210
b000000001100111 #
b00111001 -
b00001001 2
0;
#211
b1001 :
1;
#212
b000000001101000 #
b00110101 -
b00000101 2
0;
#213
b0101 :
1;
#214
b000000001101001 #
b01100110 -
01
b00110110 2
0;
#215
1;
#216
b000000001101010 #
b01101001 -
b00111001 2
0;
#217
1;
#218
b000000001101011 #
b01110110 -
b01000110 2
0;
#219
1;
#220
b000000001101100 #
b01100101 -
b00110101 2
0;
#221
1;
#222
b000000001101110 #
b00111000 -
1.
11
b00001000 2
0;
#223
03
b00000000000000000000000000000010 7
b1000 :
1;
#224
b00111001 -
0.
b00001001 2
0;
#225
13
b00000000000000000000000000000000 7
b00000000000000000000000101101000 8
b0000 9
b1111 :
1;
#226
b000000001101111 #
0;
#227
b00000000000000000000000000000001 7
b1001 9
1;
#228
b000000001110000 #
0;
#229
b1001 :
1;
#230
b000000001110001 #
b01110011 -
01
b01000011 2
0;
#231
1;
#232
b000000001110010 #
b01100101 -
b00110101 2
0;
#233
1;
#234
b000000001110011 #
b01110110 -
b01000110 2
0;
#235
1;
#236
b000000001110100 #
b01100101 -
b00110101 2
0;
#237
1;
#238
b000000001110101 #
b01101110 -
b00111110 2
0;
#239
1;
#240
b000000001110110 #
b00110011 -
11
b00000011 2
0;
#241
b0011 :
1;
#242
b000000001110111 #
b01110110 -
01
b01000110 2
0;
#243
1;
#244
b000000001111000 #
b01100100 -
b00110100 2
0;
#245
1;
#246
b000000001111001 #
b01100011 -
b00110011 2
0;
#247
1;
#248
b000000001111010 #
b01100111 -
b00110111 2
0;
#249
1;
#250
b000000001111011 #
b01110110 -
b01000110 2
0;
#251
1;
#252
b000000001111100 #
b01101101 -
b00111101 2
0;
#253
1;
#254
b000000001111101 #
b01110110 -
b01000110 2
0;
#255
1;
#256
b000000001111110 #
b01111000 -
b01001000 2
0;
#257
1;
#258
b000000001111111 #
b01110100 -
b01000100 2
0;
#259
1;
#260
b000000010000000 #
b01101010 -
b00111010 2
0;
#261
1;
#262
b000000010000001 #
b01110100 -
b01000100 2
0;
#263
1;
#264
b000000010000010 #
b01110111 -
b01000111 2
0;
#265
1;
#266
b000000010000011 #
b01101111 -
b00111111 2
0;
#267
1;
#268
b000000010000100 #
b01100100 -
b00110100 2
0;
#269
1;
#270
b000000010000101 #
b01100011 -
b00110011 2
0;
#271
1;
#272
b000000010000111 #
b00110101 -
1.
11
b00000101 2
0;
#273
03
b00000000000000000000000000000010 7
b0101 :
1;
#274
b01110100 -
0.
01
b01000100 2
0;
#275
13
b00000000000000000000000000000000 7
b00000000000000000000000111000111 8
b0000 9
b1111 :
1;
#276
b000000010001000 #
0;
#277
1;
#278
b000000010001001 #
b01101000 -
b00111000 2
0;
#279
1;
#280
b000000010001010 #
b01110010 -
b01000010 2
0;
#281
1;
#282
b000000010001011 #
b01100101 -
b00110101 2
0;
#283
1;
#284
b000000010001100 #
0;
#285
1;
#286
b000000010001101 #
b00110101 -
11
b00000101 2
0;
#287
b00000000000000000000000000000001 7
b0101 9
1;
#288
b000000010001110 #
b01100101 -
01
b00110101 2
0;
#289
1;
#290
b000000010001111 #
b01101001 -
b00111001 2
0;
#291
1;
#292
b000000010010000 #
b01100111 -
b00110111 2
0;
#293
1;
#294
b000000010010001 #
b01101000 -
b00111000 2
0;
#295
1;
#296
b000000010010010 #
b01110100 -
b01000100 2
0;
#297
1;
#298
b000000010010011 #
0;
#299
1;
#300
b000000010010100 #
b01101000 -
b00111000 2
0;
#301
1;
#302
b000000010010101 #
b01110010 -
b01000010 2
0;
#303
1;
#304
b000000010010110 #
b01100101 -
b00110101 2
0;
#305
1;
#306
b000000010010111 #
0;
#307
1;
#308
b000000010011000 #
b00110011 -
11
b00000011 2
0;
#309
b0011 :
1;
#310
b000000010011001 #
b01100110 -
01
b00110110 2
0;
#311
1;
#312
b000000010011010 #
b01101111 -
b00111111 2
0;
#313
1;
#314
b000000010011011 #
b01110101 -
b01000101 2
0;
#315
1;
#316
b000000010011100 #
b01110010 -
b01000010 2
0;
#317
1;
#318
b000000010011101 #
b00110011 -
11
b00000011 2
0;
#319
1;
#320
b000000010011110 #
b01110110 -
01
b01000110 2
0;
#321
1;
#322
b000000010011111 #
b01110100 -
b01000100 2
0;
#323
1;
#324
b000000010100000 #
b01101011 -
b00111011 2
0;
#325
1;
#326
b000000010100001 #
0;
#327
1;
#328
b000000010100010 #
b01110001 -
b01000001 2
0;
#329
1;
#330
b000000010100011 #
b01110010 -
b01000010 2
0;
#331
1;
#332
b000000010100100 #
b01100111 -
b00110111 2
0;
#333
1;
#334
b000000010100101 #
b01111000 -
b01001000 2
0;
#335
1;
#336
b000000010100111 #
b01110011 -
1.
b01000011 2
0;
#337
03
b00000000000000000000000000000010 7
1;
#338
b01100110 -
0.
b00110110 2
0;
#339
13
b00000000000000000000000000000000 7
b00000000000000000000000111111100 8
b0000 9
b1111 :
1;
#340
b000000010101000 #
0;
#341
1;
#342
b000000010101001 #
b01101111 -
b00111111 2
0;
#343
1;
#344
b000000010101010 #
b01110101 -
b01000101 2
0;
#345
1;
#346
b000000010101011 #
b01110010 -
b01000010 2
0;
#347
1;
#348
b000000010101100 #
b00111000 -
11
b00001000 2
0;
#349
b00000000000000000000000000000001 7
b1000 9
1;
#350
b000000010101101 #
b00110110 -
b00000110 2
0;
#351
b0110 :
1;
#352
b000000010101110 #
b00110011 -
b00000011 2
0;
#353
b0011 :
1;
#354
b000000010101111 #
b01101101 -
01
b00111101 2
0;
#355
1;
#356
b000000010110000 #
b01110010 -
b01000010 2
0;
#357
1;
#358
b000000010110001 #
0;
#359
1;
#360
b000000010110010 #
b01101110 -
b00111110 2
0;
#361
1;
#362
b000000010110011 #
b01110010 -
b01000010 2
0;
#363
1;
#364
b000000010110100 #
b01110011 -
b01000011 2
0;
#365
1;
#366
b000000010110101 #
b01111000 -
b01001000 2
0;
#367
1;
#368
b000000010110110 #
b01110010 -
b01000010 2
0;
#369
1;
#370
b000000010110111 #
b01101011 -
b00111011 2
0;
#371
1;
#372
b000000010111000 #
b01101111 -
b00111111 2
0;
#373
1;
#374
b000000010111001 #
b01101110 -
b00111110 2
0;
#375
1;
#376
b000000010111011 #
b01100101 -
1.
b00110101 2
0;
#377
03
b00000000000000000000000000000010 7
1;
#378
b01110011 -
0.
b01000011 2
0;
#379
13
b00000000000000000000000000000000 7
b00000000000000000000001001001111 8
b0000 9
b1111 :
1;
#380
b000000010111100 #
0;
#381
1;
#382
b000000010111101 #
b01100101 -
b00110101 2
0;
#383
1;
#384
b000000010111110 #
b01110110 -
b01000110 2
0;
#385
1;
#386
b000000010111111 #
b01100101 -
b00110101 2
0;
#387
1;
#388
b000000011000000 #
b01101110 -
b00111110 2
0;
#389
1;
#390
b000000011000001 #
0;
#391
1;
#392
b000000011000010 #
b01110100 -
b01000100 2
0;
#393
1;
#394
b000000011000011 #
b01100111 -
b00110111 2
0;
#395
1;
#396
b000000011000100 #
b01110110 -
b01000110 2
0;
#397
1;
#398
b000000011000101 #
b01101110 -
b00111110 2
0;
#399
1;
#400
b000000011000110 #
b01110010 -
b01000010 2
0;
#401
1;
#402
b000000011000111 #
0;
#403
1;
#404
b000000011001000 #
b01110001 -
b01000001 2
0;
#405
1;
#406
b000000011001001 #
b01100110 -
b00110110 2
0;
#407
1;
#408
b000000011001010 #
b01110110 -
b01000110 2
0;
#409
1;
#410
b000000011001011 #
b01111000 -
b01001000 2
0;
#411
1;
#412
b000000011001100 #
b01101000 -
b00111000 2
0;
#413
1;
#414
b000000011001101 #
b00110010 -
11
b00000010 2
0;
#415
b00000000000000000000000000000001 7
b0010 9
1;
#416
b000000011001110 #
b01110100 -
01
b01000100 2
0;
#417
1;
#418
b000000011001111 #
0;
#419
1;
#420
b000000011010000 #
b01101110 -
b00111110 2
0;
#421
1;
#422
b000000011010001 #
b01101011 -
b00111011 2
0;
#423
1;
#424
b000000011010010 #
b01100111 -
b00110111 2
0;
#425
1;
#426
b000000011010011 #
b01100110 -
b00110110 2
0;
#427
1;
#428
b000000011010100 #
0;
#429
1;
#430
b000000011010101 #
b01101111 -
b00111111 2
0;
#431
1;
#432
b000000011010110 #
b01110101 -
b01000101 2
0;
#433
1;
#434
b000000011010111 #
b01110010 -
b01000010 2
0;
#435
1;
#436
b000000011011000 #
b00111000 -
11
b00001000 2
0;
#437
b1000 :
1;
#438
b000000011011001 #
b01100110 -
01
b00110110 2
0;
#439
1;
#440
b000000011011010 #
b01101001 -
b00111001 2
0;
#441
1;
#442
b000000011011011 #
b01110110 -
b01000110 2
0;
#443
1;
#444
b000000011011100 #
b01100101 -
b00110101 2
0;
#445
1;
#446
b000000011011101 #
b01101111 -
b00111111 2
0;
#447
1;
#448
b000000011011110 #
b01101110 -
b00111110 2
0;
#449
1;
#450
b000000011100000 #
b01100101 -
1.
b00110101 2
0;
#451
03
b00000000000000000000000000000010 7
1;
#452
b00110100 -
0.
11
b00000100 2
0;
#453
13
b00000000000000000000000000000000 7
b00000000000000000000001001101011 8
b0000 9
b1111 :
1;
#454
b000000011100001 #
0;
#455
b00000000000000000000000000000001 7
b0100 9
1;
#456
b000000011100010 #
b00111001 -
b00001001 2
0;
#457
b1001 :
1;
#458
b000000011100011 #
b01100110 -
01
b00110110 2
0;
#459
1;
#460
b000000011100100 #
b01100010 -
b00110010 2
0;
#461
1;
#462
b000000011100101 #
b01110011 -
b01000011 2
0;
#463
1;
#464
b000000011100110 #
b01100110 -
b00110110 2
0;
#465
1;
#466
b000000011101000 #
b01100010 -
1.
b00110010 2
0;
#467
03
b00000000000000000000000000000010 7
1;
#468
b00110011 -
0.
11
b00000011 2
0;
#469
13
b00000000000000000000000000000000 7
b00000000000000000000001010011100 8
b0000 9
b1111 :
1;
#470
b000000011101001 #
0;
#471
b00000000000000000000000000000001 7
b0011 9
1;
#472
b000000011101010 #
b01110010 -
01
b01000010 2
0;
#473
1;
#474
b000000011101011 #
b01100010 -
b00110010 2
0;
#475
1;
#476
b000000011101100 #
b01101101 -
b00111101 2
0;
#477
1;
#478
b000000011101101 #
b01101100 -
b00111100 2
0;
#479
1;
#480
b000000011101110 #
b01110011 -
b01000011 2
0;
#481
1;
#482
b000000011101111 #
b01101011 -
b00111011 2
0;
#483
1;
#484
b000000011110000 #
b01110011 -
b01000011 2
0;
#485
1;
#486
b000000011110010 #
b01100111 -
1.
b00110111 2
0;
#487
03
b00000000000000000000000000000010 7
1;
#488
b01111010 -
0.
b01001010 2
0;
#489
13
b00000000000000000000000000000000 7
b00000000000000000000001010111101 8
b0000 9
1;
#490
b000000011110011 #
0;
#491
1;
#492
b000000011110100 #
b01110100 -
b01000100 2
0;
#493
1;
#494
b000000011110101 #
b01100111 -
b00110111 2
0;
#495
1;
#496
b000000011110110 #
b01110011 -
b01000011 2
0;
#497
1;
#498
b000000011110111 #
b01111010 -
b01001010 2
0;
#499
1;
#500
b000000011111000 #
b01110001 -
b01000001 2
0;
#501
1;
#502
b000000011111001 #
b01101010 -
b00111010 2
0;
#503
1;
#504
b000000011111010 #
0;
#505
1;
#506
b000000011111011 #
b01110011 -
b01000011 2
0;
#507
1;
#508
b000000011111100 #
b01110010 -
b01000010 2
0;
#509
1;
#510
b000000011111101 #
b01110100 -
b01000100 2
0;
#511
1;
#512
b000000011111110 #
b01101101 -
b00111101 2
0;
#513
1;
#514
b000000011111111 #
b01100111 -
b00110111 2
0;
#515
1;
#516
b000000100000000 #
b01110001 -
b01000001 2
0;
#517
1;
#518
b000000100000001 #
b01111000 -
b01001000 2
0;
#519
1;
#520
b000000100000010 #
b00110110 -
11
b00000110 2
0;
#521
b00000000000000000000000000000001 7
b0110 9
1;
#522
b000000100000011 #
b00110101 -
b00000101 2
0;
#523
b0101 :
1;
#524
b000000100000100 #
b00110111 -
b00000111 2
0;
#525
b0111 :
1;
#526
b000000100000110 #
b00110010 -
1.
b00000010 2
0;
#527
03
b00000000000000000000000000000010 7
b0010 :
1;
#528
b00110011 -
0.
b00000011 2
0;
#529
13
b00000000000000000000000000000000 7
b00000000000000000000001011111011 8
b0000 9
b1111 :
1;
#530
b000000100000111 #
0;
#531
b00000000000000000000000000000001 7
b0011 9
1;
#532
b000000100001000 #
b01100010 -
01
b00110010 2
0;
#533
1;
#534
b000000100001001 #
b01110001 -
b01000001 2
0;
#535
1;
#536
b000000100001010 #
b01101110 -
b00111110 2
0;
#537
1;
#538
b000000100001011 #
b01100110 -
b00110110 2
0;
#539
1;
#540
b000000100001100 #
b01111000 -
b01001000 2
0;
#541
1;
#542
b000000100001101 #
b01101011 -
b00111011 2
0;
#543
1;
#544
b000000100001110 #
b01100100 -
b00110100 2
0;
#545
1;
#546
b000000100001111 #
b01100010 -
b00110010 2
0;
#547
1;
#548
b000000100010000 #
b01101111 -
b00111111 2
0;
#549
1;
#550
b000000100010001 #
b01101110 -
b00111110 2
0;
#551
1;
#552
b000000100010010 #
b01100101 -
b00110101 2
0;
#553
1;
#554
b000000100010011 #
b01110011 -
b01000011 2
0;
#555
1;
#556
b000000100010100 #
b01101001 -
b00111001 2
0;
#557
1;
#558
b000000100010101 #
b01111000 -
b01001000 2
0;
#559
1;
#560
b000000100010110 #
b01110011 -
b01000011 2
0;
#561
1;
#562
b000000100010111 #
b01100101 -
b00110101 2
0;
#563
1;
#564
b000000100011000 #
b01110110 -
b01000110 2
0;
#565
1;
#566
b000000100011001 #
b01100101 -
b00110101 2
0;
#567
1;
#568
b000000100011011 #
b01101110 -
1.
b00111110 2
0;
#569
03
b00000000000000000000000000000010 7
1;
#570
b01101101 -
0.
b00111101 2
0;
#571
13
b00000000000000000000000000000000 7
b00000000000000000000001100011100 8
b0000 9
1;
#572
b000000100011100 #
0;
#573
1;
#574
b000000100011101 #
b01100110 -
b00110110 2
0;
#575
1;
#576
b000000100011110 #
b01100111 -
b00110111 2
0;
#577
1;
#578
b000000100011111 #
b01111000 -
b01001000 2
0;
#579
1;
#580
b000000100100000 #
b00110011 -
11
b00000011 2
0;
#581
b00000000000000000000000000000001 7
b0011 9
1;
#582
b000000100100001 #
b00110010 -
b00000010 2
0;
#583
b0010 :
1;
#584
b000000100100010 #
b01100110 -
01
b00110110 2
0;
#585
1;
#586
b000000100100011 #
b01110100 -
b01000100 2
0;
#587
1;
#588
b000000100100100 #
b01110000 -
b01000000 2
0;
#589
1;
#590
b000000100100101 #
b01100010 -
b00110010 2
0;
#591
1;
#592
b000000100100110 #
b01101000 -
b00111000 2
0;
#593
1;
#594
b000000100100111 #
b01100111 -
b00110111 2
0;
#595
1;
#596
b000000100101000 #
b01101110 -
b00111110 2
0;
#597
1;
#598
b000000100101001 #
b01100111 -
b00110111 2
0;
#599
1;
#600
b000000100101010 #
b01101101 -
b00111101 2
0;
#601
1;
#602
b000000100101100 #
b00110111 -
1.
11
b00000111 2
0;
#603
03
b00000000000000000000000000000010 7
b0111 :
1;
#604
b01100110 -
0.
01
b00110110 2
0;
#605
13
b00000000000000000000000000000000 7
b00000000000000000000001101000001 8
b0000 9
b1111 :
1;
#606
b000000100101101 #
0;
#607
1;
#608
b000000100101110 #
b01111010 -
b01001010 2
0;
#609
1;
#610
b000000100101111 #
b01110010 -
b01000010 2
0;
#611
1;
#612
b000000100110000 #
b01110000 -
b01000000 2
0;
#613
1;
#614
b000000100110001 #
b01100110 -
b00110110 2
0;
#615
1;
#616
b000000100110010 #
b01101000 -
b00111000 2
0;
#617
1;
#618
b000000100110011 #
b01100010 -
b00110010 2
0;
#619
1;
#620
b000000100110100 #
b01100110 -
b00110110 2
0;
#621
1;
#622
b000000100110101 #
b01110110 -
b01000110 2
0;
#623
1;
