Day_1/day1_2.sv
`timescale 1 ps / 1 ps

`define LOWER_BOUND 8'h30
`define UPPER_BOUND 8'h39

`define LOWER_BOUND_TXT 8'h61
`define UPPER_BOUND_TXT 8'h7A

`define ZERO  {8'h7A, 8'h65, 8'h72, 8'h6f}
`define ONE   {8'h6F, 8'h6E, 8'h65}
`define TWO   {8'h74, 8'h77, 8'h6F}
`define THREE {8'h74, 8'h68, 8'h72, 8'h65, 8'h65}
`define FOUR  {8'h66, 8'h6f, 8'h75, 8'h72}
`define FIVE  {8'h66, 8'h69, 8'h76, 8'h65}
`define SIX   {8'h73, 8'h69, 8'h78}
`define SEVEN {8'h73, 8'h65, 8'h76, 8'h65, 8'h6E}
`define EIGHT {8'h65, 8'h69, 8'h67, 8'h68, 8'h74}
`define NINE  {8'h6E, 8'h69, 8'h6E, 8'h65}

module day1_2 (
    input  logic clk,
    input  logic rst,

    // axis input
    input logic tvalid_rx,
    output logic tready_rx,
    input logic [7:0] tdata_rx,
    input logic tlast_rx,

    // axis output
    output logic tvalid_tx,
    input logic tready_tx,
    output logic [31:0] tdata_tx,
    output logic tlast_tx
);

typedef enum {FIRST_DIG_SEARCH, SECOND_DIG_SEARCH, DO_MAC, OUTPUT_RESULT} state_t;

// state machine register
state_t state;

// accumulator with the output value
logic [31:0] acc;

// digit registers
logic [3:0] first_dig;
logic [3:0] second_dig;

logic [4:0][7:0] sliding_window;

// convienient functions
logic is_number;
logic [7:0] num_shift;

assign is_number = (tdata_rx <= `UPPER_BOUND && tdata_rx >= `LOWER_BOUND);
assign num_shift = (tdata_rx - 8'h30);

logic [3:0] text_num;
logic [3:0] text_num_3;
logic [3:0] text_num_4;
logic [3:0] text_num_5;
logic is_number_text;

// decode the sliding window values into digits with a single hot bit if there is a valid digit decoded
always_comb begin
  case({sliding_window[1:0], tdata_rx})
    `ONE: text_num_3 = 4'h1;
    `TWO: text_num_3 = 4'h2;
    `SIX: text_num_3 = 4'h6;
    default: text_num_3 = 4'hF;
  endcase

  case({sliding_window[2:0], tdata_rx})
    `ZERO: text_num_4 = 4'h0;
    `FOUR: text_num_4 = 4'h4;
    `FIVE: text_num_4 = 4'h5;
    `NINE: text_num_4 = 4'h9;
    default: text_num_4 = 4'hF;
  endcase

  case({sliding_window[3:0], tdata_rx})
    `THREE: text_num_5 = 4'h3;
    `SEVEN: text_num_5 = 4'h7;
    `EIGHT: text_num_5 = 4'h8;
    default: text_num_5 = 4'hF;
  endcase

  assign is_number_text = (text_num_3 != 4'hF || text_num_4 != 4'hF || text_num_5 != 4'hF);

  if(text_num_3 != 4'hF) text_num = text_num_3;
  else if(text_num_4 != 4'hF) text_num = text_num_4;
  else if(text_num_5 != 4'hF) text_num = text_num_5;
end

always @(posedge clk) begin
  if(rst) begin
    state <= FIRST_DIG_SEARCH;
    acc <= '0;
    tready_rx <= 1'b0;
    first_dig <= 4'h0;
    second_dig <= 4'hF;

    tlast_tx <= 1'b0;
    tdata_tx <= '0;
    tvalid_tx <= 1'b0;

    for(integer i = 0; i < 5; i = i + 1) begin
      sliding_window[i] <= '0;
    end
  end else begin
    case (state)
      FIRST_DIG_SEARCH: begin
        tready_rx <= 1'b1;
        if(tvalid_rx) sliding_window <= {sliding_window[3:0], tdata_rx};

        if(tvalid_rx && (is_number || is_number_text)) begin
          if(is_number) begin
            first_dig <= num_shift[3:0];
          end

          if(is_number_text) begin
            first_dig <= text_num;
          end

          if(tlast_rx) begin
            state <= DO_MAC;
            tready_rx <= 1'b0;
          end
          else state <= SECOND_DIG_SEARCH;
        end
      end
      SECOND_DIG_SEARCH: begin
        tready_rx <= 1'b1;
        if(tvalid_rx) sliding_window <= {sliding_window[3:0], tdata_rx};

        if(tvalid_rx && (is_number || is_number_text)) begin
          if(is_number) begin
            second_dig <= num_shift[3:0];
          end

          if(is_number_text) begin
            second_dig <= text_num;
          end
        end

        if(tlast_rx) begin
          tready_rx <= 1'b0;
          state <= DO_MAC;
        end
      end
      DO_MAC: begin
        // tready_rx <= 1'b0;
        // reset the sliding window
        for(integer i = 0; i < 5; i = i + 1) begin
          sliding_window[i] <= '0;
        end

        if(second_dig == 4'hF) begin
          acc <= acc + (first_dig * 4'd10) + first_dig;
        end
        else acc <= acc + (first_dig * 4'd10) + second_dig;

        second_dig <= 4'hF;
        first_dig <= 4'h0;

        if(tready_tx) state <= OUTPUT_RESULT;
        else begin
          tready_rx <= 1'b1;
          state <= FIRST_DIG_SEARCH;
        end
      end
      OUTPUT_RESULT: begin
        tready_rx <= 1'b0;
        tvalid_tx <= 1'b1;
        tdata_tx <= acc;
        tlast_tx <= 1'b1;
      end
      default: state <= FIRST_DIG_SEARCH;
    endcase
  end
end



endmodule

Day_1/dut_tb.sv
`timescale 1 ps / 1 ps

`define MEM_LENGTH 21529
// `define MEM_LENGTH 93
`define PART2
// `define PART1

module dut_tb
(
    input wire clk,
    input wire rst
);

logic [$clog2(`MEM_LENGTH)-1:0] ptr;
logic [7:0] mem0 [0:`MEM_LENGTH];
logic [31:0] result [7:0];

// into DUT
logic tvalid_rx;
logic tready_rx;
logic [7:0] tdata_rx;
logic tlast_rx;

// out of DUT
logic tvalid_tx;
logic tready_tx;
logic [31:0] tdata_tx;
logic tlast_tx;

typedef enum {WRITE, READ} state_t;

state_t state;

initial begin
  $readmemh("day1.mem", mem0);
end

always @(negedge clk) begin
  if(rst) begin
    ptr <= '0;
    tvalid_rx <= 1'b0;
    tready_tx <= 1'b0;
    tdata_rx <= '0;
    tlast_rx <= 1'b0;
  end else begin
    case(state)
      WRITE: begin
        if(ptr == `MEM_LENGTH) begin
            state <= READ;
            tvalid_rx <= 1'b0;
            tready_tx <= 1'b1;
        end else begin
            tvalid_rx <= 1'b1;
            tdata_rx <= mem0[ptr];

            if(mem0[ptr+1] == 8'hFF) tlast_rx <= 1'b1;
            else tlast_rx <= 1'b0;

            if(tready_rx) begin
              if(mem0[ptr+1] == 8'hFF) ptr <= ptr + 2;
              else ptr <= ptr + 1;
            end
        end
      end
      READ: begin
        tready_tx <= 1'b1;

        result[0] <= tdata_tx;

        if(tvalid_tx) ptr <= '0;

        if(ptr == '0)
            $finish;
      end
      default: begin
        state <= WRITE;
      end
    endcase
  end
end

`ifdef PART1
day1 dut (
  .clk(clk),
  .rst(rst),

  // axis input
  .tvalid_rx(tvalid_rx),
  .tready_rx(tready_rx),
  .tdata_rx(tdata_rx),
  .tlast_rx(tlast_rx),

  // axis output
  .tvalid_tx(tvalid_tx),
  .tready_tx(tready_tx),
  .tdata_tx(tdata_tx),
  .tlast_tx(tlast_tx)
);
`endif

`ifdef PART2
day1_2 dut (
  .clk(clk),
  .rst(rst),

  // axis input
  .tvalid_rx(tvalid_rx),
  .tready_rx(tready_rx),
  .tdata_rx(tdata_rx),
  .tlast_rx(tlast_rx),

  // axis output
  .tvalid_tx(tvalid_tx),
  .tready_tx(tready_tx),
  .tdata_tx(tdata_tx),
  .tlast_tx(tlast_tx)
);
`endif



  final begin
    $writememb("result.mem", result);
  end

endmodule

Day_1/sim.vcd
$version Generated by VerilatedVcd $end
$timescale 1ps $end

 $scope module TOP $end
  $var wire  1 D clk $end
  $var wire  1 E rst $end
  $scope module dut_tb $end
   $var wire  1 D clk $end
   $var wire 15 # ptr [14:0] $end
   $var wire 32 $ result[0] [31:0] $end
   $var wire 32 % result[1] [31:0] $end
   $var wire 32 & result[2] [31:0] $end
   $var wire 32 ' result[3] [31:0] $end
   $var wire 32 ( result[4] [31:0] $end
   $var wire 32 ) result[5] [31:0] $end
   $var wire 32 * result[6] [31:0] $end
   $var wire 32 + result[7] [31:0] $end
   $var wire  1 E rst $end
   $var wire 32 0 state [31:0] $end
   $var wire  8 - tdata_rx [7:0] $end
   $var wire 32 5 tdata_tx [31:0] $end
   $var wire  1 . tlast_rx $end
   $var wire  1 6 tlast_tx $end
   $var wire  1 3 tready_rx $end
   $var wire  1 / tready_tx $end
   $var wire  1 , tvalid_rx $end
   $var wire  1 4 tvalid_tx $end
   $scope module dut $end
    $var wire 32 8 acc [31:0] $end
    $var wire  1 D clk $end
    $var wire  4 9 first_dig [3:0] $end
    $var wire  1 1 is_number $end
    $var wire  1 C is_number_text $end
    $var wire  8 2 num_shift [7:0] $end
    $var wire  1 E rst $end
    $var wire  4 : second_dig [3:0] $end
    $var wire 40 ; sliding_window [39:0] $end
    $var wire 32 7 state [31:0] $end
    $var wire  8 - tdata_rx [7:0] $end
    $var wire 32 5 tdata_tx [31:0] $end
    $var wire  4 ? text_num [3:0] $end
    $var wire  4 @ text_num_3 [3:0] $end
    $var wire  4 A text_num_4 [3:0] $end
    $var wire  4 B text_num_5 [3:0] $end
    $var wire  1 . tlast_rx $end
    $var wire  1 6 tlast_tx $end
    $var wire  1 3 tready_rx $end
    $var wire  1 / tready_tx $end
    $var wire  1 , tvalid_rx $end
    $var wire  1 4 tvalid_tx $end
    $scope module unnamedblk1 $end
     $var wire 32 = i [31:0] $end
    $upscope $end
    $scope module unnamedblk2 $end
     $var wire 32 > i [31:0] $end
    $upscope $end
   $upscope $end
  $upscope $end
 $upscope $end
$enddefinitions $end


#0
b000000000000000 #
b00000000000000000000000000000000 $
b00000000000000000000000000000000 %
b00000000000000000000000000000000 &
b00000000000000000000000000000000 '
b00000000000000000000000000000000 (
b00000000000000000000000000000000 )
b00000000000000000000000000000000 *
b00000000000000000000000000000000 +
0,
b00000000 -
0.
0/
b00000000000000000000000000000000 0
01
b11010000 2
03
04
b00000000000000000000000000000000 5
06
b00000000000000000000000000000000 7
b00000000000000000000000000000000 8
b0000 9
b0000 :
b0000000000000000000000000000000000000000 ;
b00000000000000000000000000000000 =
b00000000000000000000000000000000 >
b0000 ?
b1111 @
b1111 A
b1111 B
0C
0D
1E
#1
b1111 :
b00000000000000000000000000000101 =
1D
#2
0D
#3
1D
#4
0D
#5
13
1D
0E
#6
b000000000000001 #
1,
b00110100 -
11
b00000100 2
0D
#7
b00000000000000000000000000000001 7
b0100 9
b0000000000000000000000000000000000110100 ;
1D
#8
b000000000000010 #
b00110110 -
b00000110 2
0D
#9
b0110 :
b0000000000000000000000000011010000110110 ;
1D
#10
b000000000000011 #
b01110100 -
01
b01000100 2
0D
#11
b0000000000000000001101000011011001110100 ;
1D
#12
b000000000000100 #
b01101000 -
b00111000 2
0D
#13
b0000000000110100001101100111010001101000 ;
1D
#14
b000000000000101 #
b01110010 -
b01000010 2
0D
#15
b0011010000110110011101000110100001110010 ;
1D
#16
b000000000000110 #
b01100101 -
b00110101 2
0D
#17
b0011011001110100011010000111001001100101 ;
b0011 ?
b0011 B
1C
1D
#18
b000000000000111 #
0D
#19
b0011 :
b0111010001101000011100100110010101100101 ;
b1111 B
0C
1D
#20
b000000000001000 #
b01110110 -
b01000110 2
0D
#21
b0110100001110010011001010110010101110110 ;
1D
#22
b000000000001001 #
b01110001 -
b01000001 2
0D
#23
b0111001001100101011001010111011001110001 ;
1D
#24
b000000000001010 #
b01110011 -
b01000011 2
0D
#25
b0110010101100101011101100111000101110011 ;
1D
#26
b000000000001011 #
b00111000 -
11
b00001000 2
0D
#27
b1000 :
b0110010101110110011100010111001100111000 ;
1D
#28
b000000000001100 #
b00110001 -
b00000001 2
0D
#29
b0001 :
b0111011001110001011100110011100000110001 ;
1D
#30
b000000000001101 #
0D
#31
b0111000101110011001110000011000100110001 ;
1D
#32
b000000000001111 #
b00110100 -
1.
b00000100 2
0D
#33
03
b00000000000000000000000000000010 7
b0100 :
b0111001100111000001100010011000100110100 ;
1D
#34
b01110100 -
0.
01
b01000100 2
0D
#35
13
b00000000000000000000000000000000 7
b00000000000000000000000000101100 8
b0000 9
b1111 :
b0000000000000000000000000000000000000000 ;
b00000000000000000000000000000101 >
1D
#36
b000000000010000 #
0D
#37
b0000000000000000000000000000000001110100 ;
1D
#38
b000000000010001 #
b01101000 -
b00111000 2
0D
#39
b0000000000000000000000000111010001101000 ;
1D
#40
b000000000010010 #
b01110010 -
b01000010 2
0D
#41
b0000000000000000011101000110100001110010 ;
1D
#42
b000000000010011 #
b01100101 -
b00110101 2
0D
#43
b0000000001110100011010000111001001100101 ;
b0011 B
1C
1D
#44
b000000000010100 #
0D
#45
b00000000000000000000000000000001 7
b0011 9
b0111010001101000011100100110010101100101 ;
b1111 B
0C
1D
#46
b000000000010101 #
b01110100 -
b01000100 2
0D
#47
b0110100001110010011001010110010101110100 ;
1D
#48
b000000000010110 #
b01110111 -
b01000111 2
0D
#49
b0111001001100101011001010111010001110111 ;
1D
#50
b000000000010111 #
b01101111 -
b00111111 2
b0010 ?
b0010 @
1C
0D
#51
b0010 :
b0110010101100101011101000111011101101111 ;
b1111 @
0C
1D
#52
b000000000011000 #
0D
#53
b0110010101110100011101110110111101101111 ;
1D
#54
b000000000011001 #
b01101110 -
b00111110 2
0D
#55
b0111010001110111011011110110111101101110 ;
1D
#56
b000000000011010 #
b01100101 -
b00110101 2
b0001 ?
b0001 @
1C
0D
#57
b0001 :
b0111011101101111011011110110111001100101 ;
b1111 @
0C
1D
#58
b000000000011011 #
b01111010 -
b01001010 2
0D
#59
b0110111101101111011011100110010101111010 ;
1D
#60
b000000000011100 #
b00110001 -
11
b00000001 2
0D
#61
b0110111101101110011001010111101000110001 ;
1D
#62
b000000000011101 #
b01100111 -
01
b00110111 2
0D
#63
b0110111001100101011110100011000101100111 ;
1D
#64
b000000000011110 #
b01110100 -
b01000100 2
0D
#65
b0110010101111010001100010110011101110100 ;
1D
#66
b000000000011111 #
b01110010 -
b01000010 2
0D
#67
b0111101000110001011001110111010001110010 ;
1D
#68
b000000000100001 #
b01100100 -
1.
b00110100 2
0D
#69
03
b00000000000000000000000000000010 7
b0011000101100111011101000111001001100100 ;
1D
#70
b00110110 -
0.
11
b00000110 2
0D
#71
13
b00000000000000000000000000000000 7
b00000000000000000000000001001011 8
b0000 9
b1111 :
b0000000000000000000000000000000000000000 ;
1D
#72
b000000000100010 #
0D
#73
b00000000000000000000000000000001 7
b0110 9
b0000000000000000000000000000000000110110 ;
1D
#74
b000000000100011 #
b01100110 -
01
b00110110 2
0D
#75
b0000000000000000000000000011011001100110 ;
1D
#76
b000000000100100 #
0D
#77
b0000000000000000001101100110011001100110 ;
1D
#78
b000000000100101 #
b01111000 -
b01001000 2
0D
#79
b0000000000110110011001100110011001111000 ;
1D
#80
b000000000100110 #
b01100010 -
b00110010 2
0D
#81
b0011011001100110011001100111100001100010 ;
1D
#82
b000000000100111 #
b01110100 -
b01000100 2
0D
#83
b0110011001100110011110000110001001110100 ;
1D
#84
b000000000101000 #
b01100110 -
b00110110 2
0D
#85
b0110011001111000011000100111010001100110 ;
1D
#86
b000000000101010 #
1.
0D
#87
03
b00000000000000000000000000000010 7
b0111100001100010011101000110011001100110 ;
1D
#88
b00110111 -
0.
11
b00000111 2
0D
#89
13
b00000000000000000000000000000000 7
b00000000000000000000000010001101 8
b0000 9
b0000000000000000000000000000000000000000 ;
1D
#90
b000000000101011 #
0D
#91
b00000000000000000000000000000001 7
b0111 9
b0000000000000000000000000000000000110111 ;
1D
#92
b000000000101100 #
b00110110 -
b00000110 2
0D
#93
b0110 :
b0000000000000000000000000011011100110110 ;
1D
#94
b000000000101101 #
b00111001 -
b00001001 2
0D
#95
b1001 :
b0000000000000000001101110011011000111001 ;
1D
#96
b000000000101110 #
b01110100 -
01
b01000100 2
0D
#97
b0000000000110111001101100011100101110100 ;
1D
#98
b000000000101111 #
b01110111 -
b01000111 2
0D
#99
b0011011100110110001110010111010001110111 ;
1D
#100
b000000000110000 #
b01101111 -
b00111111 2
b0010 ?
b0010 @
1C
0D
#101
b0010 :
b0011011000111001011101000111011101101111 ;
b1111 @
0C
1D
#102
b000000000110001 #
b01110100 -
b01000100 2
0D
#103
b0011100101110100011101110110111101110100 ;
1D
#104
b000000000110010 #
b01110111 -
b01000111 2
0D
#105
b0111010001110111011011110111010001110111 ;
1D
#106
b000000000110011 #
b01101111 -
b00111111 2
b0010 @
1C
0D
#107
b0111011101101111011101000111011101101111 ;
b1111 @
0C
1D
#108
b000000000110100 #
b00110110 -
11
b00000110 2
0D
#109
b0110 :
b0110111101110100011101110110111100110110 ;
1D
#110
b000000000110101 #
b01110010 -
01
b01000010 2
0D
#111
b0111010001110111011011110011011001110010 ;
1D
#112
b000000000110110 #
b01110110 -
b01000110 2
0D
#113
b0111011101101111001101100111001001110110 ;
1D
#114
b000000000111000 #
b00111001 -
1.
11
b00001001 2
0D
#115
03
b00000000000000000000000000000010 7
b1001 :
b0110111100110110011100100111011000111001 ;
1D
#116
b01100111 -
0.
01
b00110111 2
0D
#117
13
b00000000000000000000000000000000 7
b00000000000000000000000011011100 8
b0000 9
b1111 :
b0000000000000000000000000000000000000000 ;
1D
#118
b000000000111001 #
0D
#119
b0000000000000000000000000000000001100111 ;
1D
#120
b000000000111010 #
b01101010 -
b00111010 2
0D
#121
b0000000000000000000000000110011101101010 ;
1D
#122
b000000000111011 #
b01110010 -
b01000010 2
0D
#123
b0000000000000000011001110110101001110010 ;
1D
#124
b000000000111100 #
b01100011 -
b00110011 2
0D
#125
b0000000001100111011010100111001001100011 ;
1D
#126
b000000000111101 #
b01101010 -
b00111010 2
0D
#127
b0110011101101010011100100110001101101010 ;
1D
#128
b000000000111110 #
b01110010 -
b01000010 2
0D
#129
b0110101001110010011000110110101001110010 ;
1D
#130
b000000000111111 #
b01101011 -
b00111011 2
0D
#131
b0111001001100011011010100111001001101011 ;
1D
#132
b000000001000000 #
b01110110 -
b01000110 2
0D
#133
b0110001101101010011100100110101101110110 ;
1D
#134
b000000001000001 #
b01100111 -
b00110111 2
0D
#135
b0110101001110010011010110111011001100111 ;
1D
#136
b000000001000010 #
b01101000 -
b00111000 2
0D
#137
b0111001001101011011101100110011101101000 ;
1D
#138
b000000001000011 #
b01110100 -
b01000100 2
0D
#139
b0110101101110110011001110110100001110100 ;
1D
#140
b000000001000100 #
b01101000 -
b00111000 2
0D
#141
b0111011001100111011010000111010001101000 ;
1D
#142
b000000001000101 #
b01110010 -
b01000010 2
0D
#143
b0110011101101000011101000110100001110010 ;
1D
#144
b000000001000110 #
b01100101 -
b00110101 2
0D
#145
b0110100001110100011010000111001001100101 ;
b0011 ?
b0011 B
1C
1D
#146
b000000001000111 #
0D
#147
b00000000000000000000000000000001 7
b0011 9
b0111010001101000011100100110010101100101 ;
b1111 B
0C
1D
#148
b000000001001000 #
b01100111 -
b00110111 2
0D
#149
b0110100001110010011001010110010101100111 ;
1D
#150
b000000001001001 #
b01110001 -
b01000001 2
0D
#151
b0111001001100101011001010110011101110001 ;
1D
#152
b000000001001010 #
0D
#153
b0110010101100101011001110111000101110001 ;
1D
#154
b000000001001011 #
b01110010 -
b01000010 2
0D
#155
b0110010101100111011100010111000101110010 ;
1D
#156
b000000001001100 #
b01100111 -
b00110111 2
0D
#157
b0110011101110001011100010111001001100111 ;
1D
#158
b000000001001101 #
b00111000 -
11
b00001000 2
0D
#159
b1000 :
b0111000101110001011100100110011100111000 ;
1D
#160
b000000001001110 #
b00110010 -
b00000010 2
0D
#161
b0010 :
b0111000101110010011001110011100000110010 ;
1D
#162
b000000001001111 #
b01110001 -
01
b01000001 2
0D
#163
b0111001001100111001110000011001001110001 ;
1D
#164
b000000001010000 #
b01100010 -
b00110010 2
0D
#165
b0110011100111000001100100111000101100010 ;
1D
#166
b000000001010001 #
b01100011 -
b00110011 2
0D
#167
b0011100000110010011100010110001001100011 ;
1D
#168
b000000001010011 #
b01110100 -
1.
b01000100 2
0D
#169
03
b00000000000000000000000000000010 7
b0011001001110001011000100110001101110100 ;
1D
#170
b01111010 -
0.
b01001010 2
0D
#171
13
b00000000000000000000000000000000 7
b00000000000000000000000011111100 8
b0000 9
b1111 :
b0000000000000000000000000000000000000000 ;
1D
#172
b000000001010100 #
0D
#173
b0000000000000000000000000000000001111010 ;
1D
#174
b000000001010101 #
b01101011 -
b00111011 2
0D
#175
b0000000000000000000000000111101001101011 ;
1D
#176
b000000001010110 #
b01111000 -
b01001000 2
0D
#177
b0000000000000000011110100110101101111000 ;
1D
#178
b000000001010111 #
b01101010 -
b00111010 2
0D
#179
b0000000001111010011010110111100001101010 ;
1D
#180
b000000001011000 #
b01101000 -
b00111000 2
0D
#181
b0111101001101011011110000110101001101000 ;
1D
#182
b000000001011001 #
b01100111 -
b00110111 2
0D
#183
b0110101101111000011010100110100001100111 ;
1D
#184
b000000001011010 #
b01110000 -
b01000000 2
0D
#185
b0111100001101010011010000110011101110000 ;
1D
#186
b000000001011011 #
b01110010 -
b01000010 2
0D
#187
b0110101001101000011001110111000001110010 ;
1D
#188
b000000001011100 #
b01110100 -
b01000100 2
0D
#189
b0110100001100111011100000111001001110100 ;
1D
#190
b000000001011101 #
b01110010 -
b01000010 2
0D
#191
b0110011101110000011100100111010001110010 ;
1D
#192
b000000001011110 #
b01101100 -
b00111100 2
0D
#193
b0111000001110010011101000111001001101100 ;
1D
#194
b000000001011111 #
b01100011 -
b00110011 2
0D
#195
b0111001001110100011100100110110001100011 ;
1D
#196
b000000001100000 #
b01100110 -
b00110110 2
0D
#197
b0111010001110010011011000110001101100110 ;
1D
#198
b000000001100001 #
b01100101 -
b00110101 2
0D
#199
b0111001001101100011000110110011001100101 ;
1D
#200
b000000001100010 #
b01101001 -
b00111001 2
0D
#201
b0110110001100011011001100110010101101001 ;
1D
#202
b000000001100011 #
b01100111 -
b00110111 2
0D
#203
b0110001101100110011001010110100101100111 ;
1D
#204
b000000001100100 #
b01101000 -
b00111000 2
0D
#205
b0110011001100101011010010110011101101000 ;
1D
#206
b000000001100101 #
b01110100 -
b01000100 2
b1000 ?
b1000 B
1C
0D
#207
b00000000000000000000000000000001 7
b1000 9
b0110010101101001011001110110100001110100 ;
b1111 B
0C
1D
#208
b000000001100110 #
b00110111 -
11
b00000111 2
0D
#209
b0111 :
b0110100101100111011010000111010000110111 ;
1D
#210
b000000001100111 #
b00111001 -
b00001001 2
0D
#211
b1001 :
b0110011101101000011101000011011100111001 ;
1D
#212
b000000001101000 #
b00110101 -
b00000101 2
0D
#213
b0101 :
b0110100001110100001101110011100100110101 ;
1D
#214
b000000001101001 #
b01100110 -
01
b00110110 2
0D
#215
b0111010000110111001110010011010101100110 ;
1D
#216
b000000001101010 #
b01101001 -
b00111001 2
0D
#217
b0011011100111001001101010110011001101001 ;
1D
#218
b000000001101011 #
b01110110 -
b01000110 2
0D
#219
b0011100100110101011001100110100101110110 ;
1D
#220
b000000001101100 #
b01100101 -
b00110101 2
b0101 ?
b0101 A
1C
0D
#221
b0011010101100110011010010111011001100101 ;
b1111 A
0C
1D
#222
b000000001101110 #
b00111000 -
1.
11
b00001000 2
0D
#223
03
b00000000000000000000000000000010 7
b1000 :
b0110011001101001011101100110010100111000 ;
1D
#224
b00111001 -
0.
b00001001 2
0D
#225
13
b00000000000000000000000000000000 7
b00000000000000000000000101010100 8
b0000 9
b1111 :
b0000000000000000000000000000000000000000 ;
1D
#226
b000000001101111 #
0D
#227
b00000000000000000000000000000001 7
b1001 9
b0000000000000000000000000000000000111001 ;
1D
#228
b000000001110000 #
0D
#229
b1001 :
b0000000000000000000000000011100100111001 ;
1D
#230
b000000001110001 #
b01110011 -
01
b01000011 2
0D
#231
b0000000000000000001110010011100101110011 ;
1D
#232
b000000001110010 #
b01100101 -
b00110101 2
0D
#233
b0000000000111001001110010111001101100101 ;
1D
#234
b000000001110011 #
b01110110 -
b01000110 2
0D
#235
b0011100100111001011100110110010101110110 ;
1D
#236
b000000001110100 #
b01100101 -
b00110101 2
0D
#237
b0011100101110011011001010111011001100101 ;
1D
#238
b000000001110101 #
b01101110 -
b00111110 2
b0111 ?
b0111 B
1C
0D
#239
b0111 :
b0111001101100101011101100110010101101110 ;
b1111 B
0C
1D
#240
b000000001110110 #
b00110011 -
11
b00000011 2
0D
#241
b0011 :
b0110010101110110011001010110111000110011 ;
1D
#242
b000000001110111 #
b01110110 -
01
b01000110 2
0D
#243
b0111011001100101011011100011001101110110 ;
1D
#244
b000000001111000 #
b01100100 -
b00110100 2
0D
#245
b0110010101101110001100110111011001100100 ;
1D
#246
b000000001111001 #
b01100011 -
b00110011 2
0D
#247
b0110111000110011011101100110010001100011 ;
1D
#248
b000000001111010 #
b01100111 -
b00110111 2
0D
#249
b0011001101110110011001000110001101100111 ;
1D
#250
b000000001111011 #
b01110110 -
b01000110 2
0D
#251
b0111011001100100011000110110011101110110 ;
1D
#252
b000000001111100 #
b01101101 -
b00111101 2
0D
#253
b0110010001100011011001110111011001101101 ;
1D
#254
b000000001111101 #
b01110110 -
b01000110 2
0D
#255
b0110001101100111011101100110110101110110 ;
1D
#256
b000000001111110 #
b01111000 -
b01001000 2
0D
#257
b0110011101110110011011010111011001111000 ;
1D
#258
b000000001111111 #
b01110100 -
b01000100 2
0D
#259
b0111011001101101011101100111100001110100 ;
1D
#260
b000000010000000 #
b01101010 -
b00111010 2
0D
#261
b0110110101110110011110000111010001101010 ;
1D
#262
b000000010000001 #
b01110100 -
b01000100 2
0D
#263
b0111011001111000011101000110101001110100 ;
1D
#264
b000000010000010 #
b01110111 -
b01000111 2
0D
#265
b0111100001110100011010100111010001110111 ;
1D
#266
b000000010000011 #
b01101111 -
b00111111 2
b0010 ?
b0010 @
1C
0D
#267
b0010 :
b0111010001101010011101000111011101101111 ;
b1111 @
0C
1D
#268
b000000010000100 #
b01100100 -
b00110100 2
0D
#269
b0110101001110100011101110110111101100100 ;
1D
#270
b000000010000101 #
b01100011 -
b00110011 2
0D
#271
b0111010001110111011011110110010001100011 ;
1D
#272
b000000010000111 #
b00110101 -
1.
11
b00000101 2
0D
#273
03
b00000000000000000000000000000010 7
b0101 :
b0111011101101111011001000110001100110101 ;
1D
#274
b01110100 -
0.
01
b01000100 2
0D
#275
13
b00000000000000000000000000000000 7
b00000000000000000000000110110011 8
b0000 9
b1111 :
b0000000000000000000000000000000000000000 ;
1D
#276
b000000010001000 #
0D
#277
b0000000000000000000000000000000001110100 ;
1D
#278
b000000010001001 #
b01101000 -
b00111000 2
0D
#279
b0000000000000000000000000111010001101000 ;
1D
#280
b000000010001010 #
b01110010 -
b01000010 2
0D
#281
b0000000000000000011101000110100001110010 ;
1D
#282
b000000010001011 #
b01100101 -
b00110101 2
0D
#283
b0000000001110100011010000111001001100101 ;
b0011 ?
b0011 B
1C
1D
#284
b000000010001100 #
0D
#285
b00000000000000000000000000000001 7
b0011 9
b0111010001101000011100100110010101100101 ;
b1111 B
0C
1D
#286
b000000010001101 #
b00110101 -
11
b00000101 2
0D
#287
b0101 :
b0110100001110010011001010110010100110101 ;
1D
#288
b000000010001110 #
b01100101 -
01
b00110101 2
0D
#289
b0111001001100101011001010011010101100101 ;
1D
#290
b000000010001111 #
b01101001 -
b00111001 2
0D
#291
b0110010101100101001101010110010101101001 ;
1D
#292
b000000010010000 #
b01100111 -
b00110111 2
0D
#293
b0110010100110101011001010110100101100111 ;
1D
#294
b000000010010001 #
b01101000 -
b00111000 2
0D
#295
b0011010101100101011010010110011101101000 ;
1D
#296
b000000010010010 #
b01110100 -
b01000100 2
b1000 ?
b1000 B
1C
0D
#297
b1000 :
b0110010101101001011001110110100001110100 ;
b1111 B
0C
1D
#298
b000000010010011 #
0D
#299
b0110100101100111011010000111010001110100 ;
1D
#300
b000000010010100 #
b01101000 -
b00111000 2
0D
#301
b0110011101101000011101000111010001101000 ;
1D
#302
b000000010010101 #
b01110010 -
b01000010 2
0D
#303
b0110100001110100011101000110100001110010 ;
1D
#304
b000000010010110 #
b01100101 -
b00110101 2
0D
#305
b0111010001110100011010000111001001100101 ;
b0011 ?
b0011 B
1C
1D
#306
b000000010010111 #
0D
#307
b0011 :
b0111010001101000011100100110010101100101 ;
b1111 B
0C
1D
#308
b000000010011000 #
b00110011 -
11
b00000011 2
0D
#309
b0110100001110010011001010110010100110011 ;
1D
#310
b000000010011001 #
b01100110 -
01
b00110110 2
0D
#311
b0111001001100101011001010011001101100110 ;
1D
#312
b000000010011010 #
b01101111 -
b00111111 2
0D
#313
b0110010101100101001100110110011001101111 ;
1D
#314
b000000010011011 #
b01110101 -
b01000101 2
0D
#315
b0110010100110011011001100110111101110101 ;
1D
#316
b000000010011100 #
b01110010 -
b01000010 2
b0100 ?
b0100 A
1C
0D
#317
b0100 :
b0011001101100110011011110111010101110010 ;
b1111 A
0C
1D
#318
b000000010011101 #
b00110011 -
11
b00000011 2
0D
#319
b0011 :
b0110011001101111011101010111001000110011 ;
1D
#320
b000000010011110 #
b01110110 -
01
b01000110 2
0D
#321
b0110111101110101011100100011001101110110 ;
1D
#322
b000000010011111 #
b01110100 -
b01000100 2
0D
#323
b0111010101110010001100110111011001110100 ;
1D
#324
b000000010100000 #
b01101011 -
b00111011 2
0D
#325
b0111001000110011011101100111010001101011 ;
1D
#326
b000000010100001 #
0D
#327
b0011001101110110011101000110101101101011 ;
1D
#328
b000000010100010 #
b01110001 -
b01000001 2
0D
#329
b0111011001110100011010110110101101110001 ;
1D
#330
b000000010100011 #
b01110010 -
b01000010 2
0D
#331
b0111010001101011011010110111000101110010 ;
1D
#332
b000000010100100 #
b01100111 -
b00110111 2
0D
#333
b0110101101101011011100010111001001100111 ;
1D
#334
b000000010100101 #
b01111000 -
b01001000 2
0D
#335
b0110101101110001011100100110011101111000 ;
1D
#336
b000000010100111 #
b01110011 -
1.
b01000011 2
0D
#337
03
b00000000000000000000000000000010 7
b0111000101110010011001110111100001110011 ;
1D
#338
b01100110 -
0.
b00110110 2
0D
#339
13
b00000000000000000000000000000000 7
b00000000000000000000000111010100 8
b0000 9
b1111 :
b0000000000000000000000000000000000000000 ;
1D
#340
b000000010101000 #
0D
#341
b0000000000000000000000000000000001100110 ;
1D
