Day_2/day2pt2.sv
`timescale 1 ps / 1 ps

`define LOWER_BOUND_NUM 8'h30
`define UPPER_BOUND_NUM 8'h39

//`define RED {8'h72, 8'h65, 8'h64}
//`define BLUE {8'h62, 8'h6C, 8'h75, 8'h65}
//`define GREEN {8'h67, 8'h72, 8'h65, 8'h65, 8'h6E}
`define RED   8'h72
`define BLUE  8'h62
`define GREEN 8'h67

// 237 too low
// 247 too low

`define SPACE 8'h20

module day2pt2(
  input  logic clk,
  input  logic rst,

  // axis input
  input logic tvalid_rx,
  output logic tready_rx,
  input logic [7:0] tdata_rx,
  input logic tlast_rx,

  // axis output
  output logic tvalid_tx,
  input logic tready_tx,
  output logic [31:0] tdata_tx,
  output logic tlast_tx
);

logic [31:0] acc;
logic [31:0] pow;
logic [7:0] read_val;
logic [3:0] num_shift;

logic [7:0] red_max;
logic [7:0] blue_max;
logic [7:0] green_max;

logic is_number, is_space;

assign is_number = (tdata_rx <= `UPPER_BOUND_NUM && tdata_rx >= `LOWER_BOUND_NUM);
assign is_space = (tdata_rx == `SPACE);
assign num_shift = (tdata_rx - 8'h30);


typedef enum {PARSE_FRONT, READ_NUMBER_1, READ_NUMBER_2, READ_COLOUR, OUTPUT_RESULT} state_t;

// state machine register
state_t state;

always @(posedge clk) begin
  if(rst) begin
    // reset state and accumulator
    state <= PARSE_FRONT;
    acc <= '0;
    pow <= '0;

    red_max <= '0;
    blue_max <= '0;
    green_max <= '0;

    // internal regs
    read_val <= '0;

    // AXI-S slave
    tready_rx <= 1'b0;

    // AXI-S master
    tlast_tx <= 1'b0;
    tdata_tx <= '0;
    tvalid_tx <= 1'b0;
  end else begin
    case (state)
      PARSE_FRONT: begin
        tready_rx <= 1'b1;
        red_max <= '0;
        blue_max <= '0;
        green_max <= '0;

        // this is the character for ':'
        if(tvalid_rx && tdata_rx == 8'h3A) begin
          acc <= acc + pow;
          state <= READ_NUMBER_1;
        end
        if(tready_tx) begin
          acc <= acc + pow;
          state <= OUTPUT_RESULT;
        end
      end
      READ_NUMBER_1: begin
        tready_rx <= 1'b1;

        if(tvalid_rx && is_number) begin
          read_val <= num_shift;

          state <= READ_NUMBER_2;
        end
        if(tlast_rx) begin
          state <= PARSE_FRONT;

          pow <= red_max * blue_max * green_max;
        end
      end
      READ_NUMBER_2: begin
        tready_rx <= 1'b1;

        if(tvalid_rx) begin
          if(is_number) begin
            read_val <= (read_val * 10) + num_shift;
          end

          state <= READ_COLOUR;
        end
      end
      READ_COLOUR: begin
        tready_rx <= 1'b1;

        if(tvalid_rx && ~is_space) begin
          if(`RED == tdata_rx && read_val > red_max) begin
            red_max <= read_val;
          end
          if(`BLUE == tdata_rx && read_val > blue_max) begin
            blue_max <= read_val;
          end
          if(`GREEN == tdata_rx && read_val > green_max) begin
            green_max <= read_val;
          end

          state <= READ_NUMBER_1;
        end
      end
      OUTPUT_RESULT: begin
        tready_rx <= 1'b0;
        tvalid_tx <= 1'b1;
        tdata_tx <= acc;
        tlast_tx <= 1'b1;
      end
      default: state <= PARSE_FRONT;
    endcase
  end
end



endmodule

Day_3/dut_tb.sv
`timescale 1 ps / 1 ps

`define FILE_NAME "day2.mem"

`define MEM_LENGTH 10814
// `define MEM_LENGTH 321
`define PART2
// `define PART1

module dut_tb
(
    input wire clk,
    input wire rst
);

logic [$clog2(`MEM_LENGTH)-1:0] ptr;
logic [7:0] mem0 [0:`MEM_LENGTH];
logic [31:0] result [7:0];

// into DUT
logic tvalid_rx;
logic tready_rx;
logic [7:0] tdata_rx;
logic tlast_rx;

// out of DUT
logic tvalid_tx;
logic tready_tx;
logic [31:0] tdata_tx;
logic tlast_tx;

typedef enum {WRITE, READ} state_t;

state_t state;

initial begin
  $readmemh(`FILE_NAME, mem0);
end

always @(negedge clk) begin
  if(rst) begin
    ptr <= '0;
    tvalid_rx <= 1'b0;
    tready_tx <= 1'b0;
    tdata_rx <= '0;
    tlast_rx <= 1'b0;
  end else begin
    case(state)
      WRITE: begin
        if(ptr == `MEM_LENGTH) begin
            state <= READ;
            tvalid_rx <= 1'b0;
            tready_tx <= 1'b1;
        end else begin
            tvalid_rx <= 1'b1;
            tdata_rx <= mem0[ptr];

            if(mem0[ptr+1] == 8'hFF) tlast_rx <= 1'b1;
            else tlast_rx <= 1'b0;

            if(tready_rx) begin
              if(mem0[ptr+1] == 8'hFF) ptr <= ptr + 2;
              else ptr <= ptr + 1;
            end
        end
      end
      READ: begin
        tready_tx <= 1'b1;

        result[0] <= tdata_tx;

        if(tvalid_tx) ptr <= '0;

        if(ptr == '0)
            $finish;
      end
      default: begin
        state <= WRITE;
      end
    endcase
  end
end

`ifdef PART1
day2pt1 dut (
  .clk(clk),
  .rst(rst),

  // axis input
  .tvalid_rx(tvalid_rx),
  .tready_rx(tready_rx),
  .tdata_rx(tdata_rx),
  .tlast_rx(tlast_rx),

  // axis output
  .tvalid_tx(tvalid_tx),
  .tready_tx(tready_tx),
  .tdata_tx(tdata_tx),
  .tlast_tx(tlast_tx)
);
`endif

`ifdef PART2
day2pt2 dut (
  .clk(clk),
  .rst(rst),

  // axis input
  .tvalid_rx(tvalid_rx),
  .tready_rx(tready_rx),
  .tdata_rx(tdata_rx),
  .tlast_rx(tlast_rx),

  // axis output
  .tvalid_tx(tvalid_tx),
  .tready_tx(tready_tx),
  .tdata_tx(tdata_tx),
  .tlast_tx(tlast_tx)
);
`endif



  final begin
    $writememb("result.mem", result);
  end

endmodule

Day_2/sim.vcd
$version Generated by VerilatedVcd $end
$timescale 1ps $end

 $scope module TOP $end
  $var wire  1 ? clk $end
  $var wire  1 @ rst $end
  $scope module dut_tb $end
   $var wire  1 ? clk $end
   $var wire 14 # ptr [13:0] $end
   $var wire 32 $ result[0] [31:0] $end
   $var wire 32 % result[1] [31:0] $end
   $var wire 32 & result[2] [31:0] $end
   $var wire 32 ' result[3] [31:0] $end
   $var wire 32 ( result[4] [31:0] $end
   $var wire 32 ) result[5] [31:0] $end
   $var wire 32 * result[6] [31:0] $end
   $var wire 32 + result[7] [31:0] $end
   $var wire  1 @ rst $end
   $var wire 32 0 state [31:0] $end
   $var wire  8 - tdata_rx [7:0] $end
   $var wire 32 6 tdata_tx [31:0] $end
   $var wire  1 . tlast_rx $end
   $var wire  1 7 tlast_tx $end
   $var wire  1 4 tready_rx $end
   $var wire  1 / tready_tx $end
   $var wire  1 , tvalid_rx $end
   $var wire  1 5 tvalid_tx $end
   $scope module dut $end
    $var wire 32 8 acc [31:0] $end
    $var wire  8 < blue_max [7:0] $end
    $var wire  1 ? clk $end
    $var wire  8 = green_max [7:0] $end
    $var wire  1 2 is_number $end
    $var wire  1 3 is_space $end
    $var wire  4 1 num_shift [3:0] $end
    $var wire 32 9 pow [31:0] $end
    $var wire  8 : read_val [7:0] $end
    $var wire  8 ; red_max [7:0] $end
    $var wire  1 @ rst $end
    $var wire 32 > state [31:0] $end
    $var wire  8 - tdata_rx [7:0] $end
    $var wire 32 6 tdata_tx [31:0] $end
    $var wire  1 . tlast_rx $end
    $var wire  1 7 tlast_tx $end
    $var wire  1 4 tready_rx $end
    $var wire  1 / tready_tx $end
    $var wire  1 , tvalid_rx $end
    $var wire  1 5 tvalid_tx $end
   $upscope $end
  $upscope $end
 $upscope $end
$enddefinitions $end


#0
b00000000000000 #
b00000000000000000000000000000000 $
b00000000000000000000000000000000 %
b00000000000000000000000000000000 &
b00000000000000000000000000000000 '
b00000000000000000000000000000000 (
b00000000000000000000000000000000 )
b00000000000000000000000000000000 *
b00000000000000000000000000000000 +
0,
b00000000 -
0.
0/
b00000000000000000000000000000000 0
b0000 1
02
03
04
05
b00000000000000000000000000000000 6
07
b00000000000000000000000000000000 8
b00000000000000000000000000000000 9
b00000000 :
b00000000 ;
b00000000 <
b00000000 =
b00000000000000000000000000000000 >
0?
1@
#1
1?
#2
0?
#3
1?
#4
0?
#5
14
1?
0@
#6
b00000000000001 #
1,
b01000111 -
b0111 1
0?
#7
1?
#8
b00000000000010 #
b01100001 -
b0001 1
0?
#9
1?
#10
b00000000000011 #
b01101101 -
b1101 1
0?
#11
1?
#12
b00000000000100 #
b01100101 -
b0101 1
0?
#13
1?
#14
b00000000000101 #
b00100000 -
b0000 1
13
0?
#15
1?
#16
b00000000000110 #
b00110001 -
b0001 1
12
03
0?
#17
1?
#18
b00000000000111 #
b00111010 -
b1010 1
02
0?
#19
b00000000000000000000000000000001 >
1?
#20
b00000000001000 #
b00100000 -
b0000 1
13
0?
#21
1?
#22
b00000000001001 #
b00110111 -
b0111 1
12
03
0?
#23
b00000111 :
b00000000000000000000000000000010 >
1?
#24
b00000000001010 #
b00100000 -
b0000 1
02
13
0?
#25
b00000000000000000000000000000011 >
1?
#26
b00000000001011 #
b01100010 -
b0010 1
03
0?
#27
b00000111 <
b00000000000000000000000000000001 >
1?
#28
b00000000001100 #
b01101100 -
b1100 1
0?
#29
1?
#30
b00000000001101 #
b01110101 -
b0101 1
0?
#31
1?
#32
b00000000001110 #
b01100101 -
0?
#33
1?
#34
b00000000001111 #
b00101100 -
b1100 1
0?
#35
1?
#36
b00000000010000 #
b00100000 -
b0000 1
13
0?
#37
1?
#38
b00000000010001 #
b00111001 -
b1001 1
12
03
0?
#39
b00001001 :
b00000000000000000000000000000010 >
1?
#40
b00000000010010 #
b00100000 -
b0000 1
02
13
0?
#41
b00000000000000000000000000000011 >
1?
#42
b00000000010011 #
b01110010 -
b0010 1
03
0?
#43
b00001001 ;
b00000000000000000000000000000001 >
1?
#44
b00000000010100 #
b01100101 -
b0101 1
0?
#45
1?
#46
b00000000010101 #
b01100100 -
b0100 1
0?
#47
1?
#48
b00000000010110 #
b00101100 -
b1100 1
0?
#49
1?
#50
b00000000010111 #
b00100000 -
b0000 1
13
0?
#51
1?
#52
b00000000011000 #
b00110001 -
b0001 1
12
03
0?
#53
b00000001 :
b00000000000000000000000000000010 >
1?
#54
b00000000011001 #
b00100000 -
b0000 1
02
13
0?
#55
b00000000000000000000000000000011 >
1?
#56
b00000000011010 #
b01100111 -
b0111 1
03
0?
#57
b00000001 =
b00000000000000000000000000000001 >
1?
#58
b00000000011011 #
b01110010 -
b0010 1
0?
#59
1?
#60
b00000000011100 #
b01100101 -
b0101 1
0?
#61
1?
#62
b00000000011101 #
0?
#63
1?
#64
b00000000011110 #
b01101110 -
b1110 1
0?
#65
1?
#66
b00000000011111 #
b00111011 -
b1011 1
0?
#67
1?
#68
b00000000100000 #
b00100000 -
b0000 1
13
0?
#69
1?
#70
b00000000100001 #
b00111000 -
b1000 1
12
03
0?
#71
b00001000 :
b00000000000000000000000000000010 >
1?
#72
b00000000100010 #
b00100000 -
b0000 1
02
13
0?
#73
b00000000000000000000000000000011 >
1?
#74
b00000000100011 #
b01100111 -
b0111 1
03
0?
#75
b00001000 =
b00000000000000000000000000000001 >
1?
#76
b00000000100100 #
b01110010 -
b0010 1
0?
#77
1?
#78
b00000000100101 #
b01100101 -
b0101 1
0?
#79
1?
#80
b00000000100110 #
0?
#81
1?
#82
b00000000100111 #
b01101110 -
b1110 1
0?
#83
1?
#84
b00000000101000 #
b00111011 -
b1011 1
0?
#85
1?
#86
b00000000101001 #
b00100000 -
b0000 1
13
0?
#87
1?
#88
b00000000101010 #
b00110001 -
b0001 1
12
03
0?
#89
b00000001 :
b00000000000000000000000000000010 >
1?
#90
b00000000101011 #
b00110000 -
b0000 1
0?
#91
b00001010 :
b00000000000000000000000000000011 >
1?
#92
b00000000101100 #
b00100000 -
02
13
0?
#93
1?
#94
b00000000101101 #
b01100111 -
b0111 1
03
0?
#95
b00001010 =
b00000000000000000000000000000001 >
1?
#96
b00000000101110 #
b01110010 -
b0010 1
0?
#97
1?
#98
b00000000101111 #
b01100101 -
b0101 1
0?
#99
1?
#100
b00000000110000 #
0?
#101
1?
#102
b00000000110001 #
b01101110 -
b1110 1
0?
#103
1?
#104
b00000000110010 #
b00101100 -
b1100 1
0?
#105
1?
#106
b00000000110011 #
b00100000 -
b0000 1
13
0?
#107
1?
#108
b00000000110100 #
b00110101 -
b0101 1
12
03
0?
#109
b00000101 :
b00000000000000000000000000000010 >
1?
#110
b00000000110101 #
b00100000 -
b0000 1
02
13
0?
#111
b00000000000000000000000000000011 >
1?
#112
b00000000110110 #
b01100010 -
b0010 1
03
0?
#113
b00000000000000000000000000000001 >
1?
#114
b00000000110111 #
b01101100 -
b1100 1
0?
#115
1?
#116
b00000000111000 #
b01110101 -
b0101 1
0?
#117
1?
#118
b00000000111001 #
b01100101 -
0?
#119
1?
#120
b00000000111010 #
b00101100 -
b1100 1
0?
#121
1?
#122
b00000000111011 #
b00100000 -
b0000 1
13
0?
#123
1?
#124
b00000000111100 #
b00110011 -
b0011 1
12
03
0?
#125
b00000011 :
b00000000000000000000000000000010 >
1?
#126
b00000000111101 #
b00100000 -
b0000 1
02
13
0?
#127
b00000000000000000000000000000011 >
1?
#128
b00000000111110 #
b01110010 -
b0010 1
03
0?
#129
b00000000000000000000000000000001 >
1?
#130
b00000000111111 #
b01100101 -
b0101 1
0?
#131
1?
#132
b00000001000000 #
b01100100 -
b0100 1
0?
#133
1?
#134
b00000001000001 #
b00111011 -
b1011 1
0?
#135
1?
#136
b00000001000010 #
b00100000 -
b0000 1
13
0?
#137
1?
#138
b00000001000011 #
b00110001 -
b0001 1
12
03
0?
#139
b00000001 :
b00000000000000000000000000000010 >
1?
#140
b00000001000100 #
0?
#141
b00001011 :
b00000000000000000000000000000011 >
1?
#142
b00000001000101 #
b00100000 -
b0000 1
02
13
0?
#143
1?
#144
b00000001000110 #
b01100010 -
b0010 1
03
0?
#145
b00001011 <
b00000000000000000000000000000001 >
1?
#146
b00000001000111 #
b01101100 -
b1100 1
0?
#147
1?
#148
b00000001001000 #
b01110101 -
b0101 1
0?
#149
1?
#150
b00000001001001 #
b01100101 -
0?
#151
1?
#152
b00000001001010 #
b00101100 -
b1100 1
0?
#153
1?
#154
b00000001001011 #
b00100000 -
b0000 1
13
0?
#155
1?
#156
b00000001001100 #
b00110101 -
b0101 1
12
03
0?
#157
b00000101 :
b00000000000000000000000000000010 >
1?
#158
b00000001001101 #
b00100000 -
b0000 1
02
13
0?
#159
b00000000000000000000000000000011 >
1?
#160
b00000001001110 #
b01110010 -
b0010 1
03
0?
#161
b00000000000000000000000000000001 >
1?
#162
b00000001001111 #
b01100101 -
b0101 1
0?
#163
1?
#164
b00000001010000 #
b01100100 -
b0100 1
0?
#165
1?
#166
b00000001010001 #
b00101100 -
b1100 1
0?
#167
1?
#168
b00000001010010 #
b00100000 -
b0000 1
13
0?
#169
1?
#170
b00000001010011 #
b00110001 -
b0001 1
12
03
0?
#171
b00000001 :
b00000000000000000000000000000010 >
1?
#172
b00000001010100 #
b00100000 -
b0000 1
02
13
0?
#173
b00000000000000000000000000000011 >
1?
#174
b00000001010101 #
b01100111 -
b0111 1
03
0?
#175
b00000000000000000000000000000001 >
1?
#176
b00000001010110 #
b01110010 -
b0010 1
0?
#177
1?
#178
b00000001010111 #
b01100101 -
b0101 1
0?
#179
1?
#180
b00000001011000 #
0?
#181
1?
#182
b00000001011010 #
b01101110 -
1.
b1110 1
0?
#183
b00000000000000000000001111011110 9
b00000000000000000000000000000000 >
1?
#184
b00000001011011 #
b01000111 -
0.
b0111 1
0?
#185
b00000000 ;
b00000000 <
b00000000 =
1?
#186
b00000001011100 #
b01100001 -
b0001 1
0?
#187
1?
#188
b00000001011101 #
b01101101 -
b1101 1
0?
#189
1?
#190
b00000001011110 #
b01100101 -
b0101 1
0?
#191
1?
#192
b00000001011111 #
b00100000 -
b0000 1
13
0?
#193
1?
#194
b00000001100000 #
b00110010 -
b0010 1
12
03
0?
#195
1?
#196
b00000001100001 #
b00111010 -
b1010 1
02
0?
#197
b00000000000000000000001111011110 8
b00000000000000000000000000000001 >
1?
#198
b00000001100010 #
b00100000 -
b0000 1
13
0?
#199
1?
#200
b00000001100011 #
b00110111 -
b0111 1
12
03
0?
#201
b00000111 :
b00000000000000000000000000000010 >
1?
#202
b00000001100100 #
b00100000 -
b0000 1
02
13
0?
#203
b00000000000000000000000000000011 >
1?
#204
b00000001100101 #
b01100111 -
b0111 1
03
0?
#205
b00000111 =
b00000000000000000000000000000001 >
1?
#206
b00000001100110 #
b01110010 -
b0010 1
0?
#207
1?
#208
b00000001100111 #
b01100101 -
b0101 1
0?
#209
1?
#210
b00000001101000 #
0?
#211
1?
#212
b00000001101001 #
b01101110 -
b1110 1
0?
#213
1?
#214
b00000001101010 #
b00101100 -
b1100 1
0?
#215
1?
#216
b00000001101011 #
b00100000 -
b0000 1
13
0?
#217
1?
#218
b00000001101100 #
b00110011 -
b0011 1
12
03
0?
#219
b00000011 :
b00000000000000000000000000000010 >
1?
#220
b00000001101101 #
b00100000 -
b0000 1
02
13
0?
#221
b00000000000000000000000000000011 >
1?
#222
b00000001101110 #
b01100010 -
b0010 1
03
0?
#223
b00000011 <
b00000000000000000000000000000001 >
1?
#224
b00000001101111 #
b01101100 -
b1100 1
0?
#225
1?
#226
b00000001110000 #
b01110101 -
b0101 1
0?
#227
1?
#228
b00000001110001 #
b01100101 -
0?
#229
1?
#230
b00000001110010 #
b00111011 -
b1011 1
0?
#231
1?
#232
b00000001110011 #
b00100000 -
b0000 1
13
0?
#233
1?
#234
b00000001110100 #
b00110010 -
b0010 1
12
03
0?
#235
b00000010 :
b00000000000000000000000000000010 >
1?
#236
b00000001110101 #
b00110000 -
b0000 1
0?
#237
b00010100 :
b00000000000000000000000000000011 >
1?
#238
b00000001110110 #
b00100000 -
02
13
0?
#239
1?
#240
b00000001110111 #
b01100010 -
b0010 1
03
0?
#241
b00010100 <
b00000000000000000000000000000001 >
1?
#242
b00000001111000 #
b01101100 -
b1100 1
0?
#243
1?
#244
b00000001111001 #
b01110101 -
b0101 1
0?
#245
1?
#246
b00000001111010 #
b01100101 -
0?
#247
1?
#248
b00000001111011 #
b00101100 -
b1100 1
0?
#249
1?
#250
b00000001111100 #
b00100000 -
b0000 1
13
0?
#251
1?
#252
b00000001111101 #
b00110100 -
b0100 1
12
03
0?
#253
b00000100 :
b00000000000000000000000000000010 >
1?
#254
b00000001111110 #
b00100000 -
b0000 1
02
13
0?
#255
b00000000000000000000000000000011 >
1?
#256
b00000001111111 #
b01100111 -
b0111 1
03
0?
#257
b00000000000000000000000000000001 >
1?
#258
b00000010000000 #
b01110010 -
b0010 1
0?
#259
1?
#260
b00000010000001 #
b01100101 -
b0101 1
0?
#261
1?
#262
b00000010000010 #
0?
#263
1?
#264
b00000010000011 #
b01101110 -
b1110 1
0?
#265
1?
#266
b00000010000100 #
b00111011 -
b1011 1
0?
#267
1?
#268
b00000010000101 #
b00100000 -
b0000 1
13
0?
#269
1?
#270
b00000010000110 #
b00110110 -
b0110 1
12
03
0?
#271
b00000110 :
b00000000000000000000000000000010 >
1?
#272
b00000010000111 #
b00100000 -
b0000 1
02
13
0?
#273
b00000000000000000000000000000011 >
1?
#274
b00000010001000 #
b01110010 -
b0010 1
03
0?
#275
b00000110 ;
b00000000000000000000000000000001 >
1?
#276
b00000010001001 #
b01100101 -
b0101 1
0?
#277
1?
#278
b00000010001010 #
b01100100 -
b0100 1
0?
#279
1?
#280
b00000010001011 #
b00101100 -
b1100 1
0?
#281
1?
#282
b00000010001100 #
b00100000 -
b0000 1
13
0?
#283
1?
#284
b00000010001101 #
b00110001 -
b0001 1
12
03
0?
#285
b00000001 :
b00000000000000000000000000000010 >
1?
#286
b00000010001110 #
b00110011 -
b0011 1
0?
#287
b00001101 :
b00000000000000000000000000000011 >
1?
#288
b00000010001111 #
b00100000 -
b0000 1
02
13
0?
#289
1?
#290
b00000010010000 #
b01100010 -
b0010 1
03
0?
#291
b00000000000000000000000000000001 >
1?
#292
b00000010010001 #
b01101100 -
b1100 1
0?
#293
1?
#294
b00000010010010 #
b01110101 -
b0101 1
0?
#295
1?
#296
b00000010010011 #
b01100101 -
0?
#297
1?
#298
b00000010010100 #
b00101100 -
b1100 1
0?
#299
1?
#300
b00000010010101 #
b00100000 -
b0000 1
13
0?
#301
1?
#302
b00000010010110 #
b00110010 -
b0010 1
12
03
0?
#303
b00000010 :
b00000000000000000000000000000010 >
1?
#304
b00000010010111 #
b00100000 -
b0000 1
02
13
0?
#305
b00000000000000000000000000000011 >
1?
#306
b00000010011000 #
b01100111 -
b0111 1
03
0?
#307
b00000000000000000000000000000001 >
1?
#308
b00000010011001 #
b01110010 -
b0010 1
0?
#309
1?
#310
b00000010011010 #
b01100101 -
b0101 1
0?
#311
1?
#312
b00000010011011 #
0?
#313
1?
#314
b00000010011101 #
b01101110 -
1.
b1110 1
0?
#315
b00000000000000000000001101001000 9
b00000000000000000000000000000000 >
1?
#316
b00000010011110 #
b01000111 -
0.
b0111 1
0?
#317
b00000000 ;
b00000000 <
b00000000 =
1?
#318
b00000010011111 #
b01100001 -
b0001 1
0?
#319
1?
#320
b00000010100000 #
b01101101 -
b1101 1
0?
#321
1?
#322
b00000010100001 #
b01100101 -
b0101 1
0?
#323
1?
#324
b00000010100010 #
b00100000 -
b0000 1
13
0?
#325
1?
#326
b00000010100011 #
b00110011 -
b0011 1
12
03
0?
#327
1?
#328
b00000010100100 #
b00111010 -
b1010 1
02
0?
#329
b00000000000000000000011100100110 8
b00000000000000000000000000000001 >
1?
#330
b00000010100101 #
b00100000 -
b0000 1
13
0?
#331
1?
#332
b00000010100110 #
b00110001 -
b0001 1
12
03
0?
#333
b00000001 :
b00000000000000000000000000000010 >
1?
#334
b00000010100111 #
0?
#335
b00001011 :
b00000000000000000000000000000011 >
1?
#336
b00000010101000 #
b00100000 -
b0000 1
02
13
0?
#337
1?
#338
b00000010101001 #
b01100010 -
b0010 1
03
0?
#339
b00001011 <
b00000000000000000000000000000001 >
1?
#340
b00000010101010 #
b01101100 -
b1100 1
0?
#341
1?
#342
b00000010101011 #
b01110101 -
b0101 1
0?
#343
1?
#344
b00000010101100 #
b01100101 -
0?
#345
1?
#346
b00000010101101 #
b00101100 -
b1100 1
0?
#347
1?
#348
b00000010101110 #
b00100000 -
b0000 1
13
0?
#349
1?
#350
b00000010101111 #
b00110011 -
b0011 1
12
03
0?
#351
b00000011 :
b00000000000000000000000000000010 >
1?
#352
b00000010110000 #
b00100000 -
b0000 1
02
13
0?
#353
b00000000000000000000000000000011 >
1?
#354
b00000010110001 #
b01110010 -
b0010 1
03
0?
#355
b00000011 ;
b00000000000000000000000000000001 >
1?
#356
b00000010110010 #
b01100101 -
b0101 1
0?
#357
1?
#358
b00000010110011 #
b01100100 -
b0100 1
0?
#359
1?
#360
b00000010110100 #
b00101100 -
b1100 1
0?
#361
1?
#362
b00000010110101 #
b00100000 -
b0000 1
13
0?
#363
1?
#364
b00000010110110 #
b00110001 -
b0001 1
12
03
0?
#365
b00000001 :
b00000000000000000000000000000010 >
1?
#366
b00000010110111 #
b00100000 -
b0000 1
02
13
0?
#367
b00000000000000000000000000000011 >
1?
#368
b00000010111000 #
b01100111 -
b0111 1
03
0?
#369
b00000001 =
b00000000000000000000000000000001 >
1?
#370
b00000010111001 #
b01110010 -
b0010 1
0?
#371
1?
#372
b00000010111010 #
b01100101 -
b0101 1
0?
#373
1?
#374
b00000010111011 #
0?
#375
1?
#376
b00000010111100 #
b01101110 -
b1110 1
0?
#377
1?
#378
b00000010111101 #
b00111011 -
b1011 1
0?
#379
1?
#380
b00000010111110 #
b00100000 -
b0000 1
13
0?
#381
1?
#382
b00000010111111 #
b00110001 -
b0001 1
12
03
0?
#383
b00000000000000000000000000000010 >
1?
#384
b00000011000000 #
b00110101 -
b0101 1
0?
#385
b00001111 :
b00000000000000000000000000000011 >
1?
#386
b00000011000001 #
b00100000 -
b0000 1
02
13
0?
#387
1?
#388
b00000011000010 #
b01110010 -
b0010 1
03
0?
#389
b00001111 ;
b00000000000000000000000000000001 >
1?
#390
b00000011000011 #
b01100101 -
b0101 1
0?
#391
1?
#392
b00000011000100 #
b01100100 -
b0100 1
0?
#393
1?
#394
b00000011000101 #
b00101100 -
b1100 1
0?
#395
1?
#396
b00000011000110 #
b00100000 -
b0000 1
13
0?
#397
1?
#398
b00000011000111 #
b00111001 -
b1001 1
12
03
0?
#399
b00001001 :
b00000000000000000000000000000010 >
1?
#400
b00000011001000 #
b00100000 -
b0000 1
02
13
0?
#401
b00000000000000000000000000000011 >
1?
#402
b00000011001001 #
b01100010 -
b0010 1
03
0?
#403
b00000000000000000000000000000001 >
1?
#404
b00000011001010 #
b01101100 -
b1100 1
0?
#405
1?
#406
b00000011001011 #
b01110101 -
b0101 1
0?
#407
1?
#408
b00000011001100 #
b01100101 -
0?
#409
1?
#410
b00000011001101 #
b00101100 -
b1100 1
0?
#411
1?
#412
b00000011001110 #
b00100000 -
b0000 1
13
0?
#413
1?
#414
b00000011001111 #
b00110011 -
b0011 1
12
03
0?
#415
b00000011 :
b00000000000000000000000000000010 >
1?
#416
b00000011010000 #
b00100000 -
b0000 1
02
13
0?
#417
b00000000000000000000000000000011 >
1?
#418
b00000011010001 #
b01100111 -
b0111 1
03
0?
#419
b00000011 =
b00000000000000000000000000000001 >
1?
#420
b00000011010010 #
b01110010 -
b0010 1
0?
#421
1?
#422
b00000011010011 #
b01100101 -
b0101 1
0?
#423
1?
#424
b00000011010100 #
0?
#425
1?
#426
b00000011010101 #
b01101110 -
b1110 1
0?
#427
1?
#428
b00000011010110 #
b00111011 -
b1011 1
0?
#429
1?
#430
b00000011010111 #
b00100000 -
b0000 1
13
0?
#431
1?
#432
b00000011011000 #
b00110001 -
b0001 1
12
03
0?
#433
b00000001 :
b00000000000000000000000000000010 >
1?
#434
b00000011011001 #
0?
#435
b00001011 :
b00000000000000000000000000000011 >
1?
#436
b00000011011010 #
b00100000 -
b0000 1
02
13
0?
#437
1?
#438
b00000011011011 #
b01100010 -
b0010 1
03
0?
#439
b00000000000000000000000000000001 >
1?
#440
b00000011011100 #
b01101100 -
b1100 1
0?
#441
1?
#442
b00000011011101 #
b01110101 -
b0101 1
0?
#443
1?
#444
b00000011011110 #
b01100101 -
0?
#445
1?
#446
b00000011011111 #
b00101100 -
b1100 1
0?
#447
1?
#448
b00000011100000 #
b00100000 -
b0000 1
13
0?
#449
1?
#450
b00000011100001 #
b00110100 -
b0100 1
12
03
0?
#451
b00000100 :
b00000000000000000000000000000010 >
1?
#452
b00000011100010 #
b00100000 -
b0000 1
02
13
0?
#453
b00000000000000000000000000000011 >
1?
#454
b00000011100011 #
b01110010 -
b0010 1
03
0?
#455
b00000000000000000000000000000001 >
1?
#456
b00000011100100 #
b01100101 -
b0101 1
0?
#457
1?
#458
b00000011100101 #
b01100100 -
b0100 1
0?
#459
1?
#460
b00000011100110 #
b00101100 -
b1100 1
0?
#461
1?
#462
b00000011100111 #
b00100000 -
b0000 1
13
0?
#463
1?
#464
b00000011101000 #
b00110100 -
b0100 1
12
03
0?
#465
b00000000000000000000000000000010 >
1?
#466
b00000011101001 #
b00100000 -
b0000 1
02
13
0?
#467
b00000000000000000000000000000011 >
1?
#468
b00000011101010 #
b01100111 -
b0111 1
03
0?
#469
b00000100 =
b00000000000000000000000000000001 >
1?
#470
b00000011101011 #
b01110010 -
b0010 1
0?
#471
1?
#472
b00000011101100 #
b01100101 -
b0101 1
0?
#473
1?
#474
b00000011101101 #
0?
#475
1?
#476
b00000011101110 #
b01101110 -
b1110 1
0?
#477
1?
#478
b00000011101111 #
b00111011 -
b1011 1
0?
#479
1?
#480
b00000011110000 #
b00100000 -
b0000 1
13
0?
#481
1?
#482
b00000011110001 #
b00110001 -
b0001 1
12
03
0?
#483
b00000001 :
b00000000000000000000000000000010 >
1?
#484
b00000011110010 #
b00100000 -
b0000 1
02
13
0?
#485
b00000000000000000000000000000011 >
1?
#486
b00000011110011 #
b01110010 -
b0010 1
03
0?
#487
b00000000000000000000000000000001 >
1?
#488
b00000011110100 #
b01100101 -
b0101 1
0?
#489
1?
#490
b00000011110101 #
b01100100 -
b0100 1
0?
#491
1?
#492
b00000011110110 #
b00101100 -
b1100 1
0?
#493
1?
#494
b00000011110111 #
b00100000 -
b0000 1
13
0?
#495
1?
#496
b00000011111000 #
b00110010 -
b0010 1
12
03
0?
#497
b00000010 :
b00000000000000000000000000000010 >
1?
#498
b00000011111001 #
b00100000 -
b0000 1
02
13
0?
#499
b00000000000000000000000000000011 >
1?
#500
b00000011111010 #
b01100111 -
b0111 1
03
0?
#501
b00000000000000000000000000000001 >
1?
#502
b00000011111011 #
b01110010 -
b0010 1
0?
#503
1?
#504
b00000011111100 #
b01100101 -
b0101 1
0?
#505
1?
#506
b00000011111101 #
0?
#507
1?
#508
b00000011111110 #
b01101110 -
b1110 1
0?
#509
1?
#510
b00000011111111 #
b00101100 -
b1100 1
0?
#511
1?
#512
b00000100000000 #
b00100000 -
b0000 1
13
0?
#513
1?
#514
b00000100000001 #
b00110001 -
b0001 1
12
03
0?
#515
b00000001 :
b00000000000000000000000000000010 >
1?
#516
b00000100000010 #
b00110100 -
b0100 1
0?
#517
b00001110 :
b00000000000000000000000000000011 >
1?
#518
b00000100000011 #
b00100000 -
b0000 1
02
13
0?
#519
1?
#520
b00000100000100 #
b01100010 -
b0010 1
03
0?
#521
b00001110 <
b00000000000000000000000000000001 >
1?
#522
b00000100000101 #
b01101100 -
b1100 1
0?
#523
1?
#524
b00000100000110 #
b01110101 -
b0101 1
0?
#525
1?
#526
b00000100000111 #
b01100101 -
0?
#527
1?
#528
b00000100001000 #
b00111011 -
b1011 1
0?
#529
1?
#530
b00000100001001 #
b00100000 -
b0000 1
13
0?
#531
1?
#532
b00000100001010 #
b00110001 -
b0001 1
12
03
0?
#533
b00000001 :
b00000000000000000000000000000010 >
1?
#534
b00000100001011 #
b00111000 -
b1000 1
0?
