Day_1/day1_2.sv
`timescale 1 ps / 1 ps

`define LOWER_BOUND 8'h30
`define UPPER_BOUND 8'h39

`define LOWER_BOUND_TXT 8'h61
`define UPPER_BOUND_TXT 8'h7A

`define ZERO  {8'h7A, 8'h65, 8'h72, 8'h6f}
`define ONE   {8'h6F, 8'h6E, 8'h65}
`define TWO   {8'h74, 8'h77, 8'h6F}
`define THREE {8'h74, 8'h68, 8'h72, 8'h65, 8'h65}
`define FOUR  {8'h66, 8'h6f, 8'h75, 8'h72}
`define FIVE  {8'h66, 8'h69, 8'h76, 8'h65}
`define SIX   {8'h73, 8'h69, 8'h78}
`define SEVEN {8'h73, 8'h65, 8'h76, 8'h65, 8'h6E}
`define EIGHT {8'h65, 8'h69, 8'h67, 8'h68, 8'h74}
`define NINE  {8'h6E, 8'h69, 8'h6E, 8'h65}

module day1_2 (
    input  logic clk,
    input  logic rst,

    // axis input
    input logic tvalid_rx,
    output logic tready_rx,
    input logic [7:0] tdata_rx,
    input logic tlast_rx,

    // axis output
    output logic tvalid_tx,
    input logic tready_tx,
    output logic [31:0] tdata_tx,
    output logic tlast_tx
);

typedef enum {FIRST_DIG_SEARCH, SECOND_DIG_SEARCH, DO_MAC, OUTPUT_RESULT} state_t;

// state machine register
state_t state;

// accumulator with the output value
logic [31:0] acc;

// digit registers
logic [3:0] first_dig;
logic [3:0] second_dig;

logic [3:0][7:0] sliding_window;

// convienient functions
logic is_number;
logic [3:0] num_shift;

assign is_number = (tdata_rx <= `UPPER_BOUND && tdata_rx >= `LOWER_BOUND);
assign num_shift = (tdata_rx - 8'h30);

logic [3:0] text_num;
logic [3:0] text_num_3;
logic [3:0] text_num_4;
logic [3:0] text_num_5;
logic is_number_text;

// decode the sliding window values into digits with a single hot bit if there is a valid digit decoded
always_comb begin
  case({sliding_window[1:0], tdata_rx})
    `ONE: text_num_3 = 4'h1;
    `TWO: text_num_3 = 4'h2;
    `SIX: text_num_3 = 4'h6;
    default: text_num_3 = 4'hF;
  endcase

  case({sliding_window[2:0], tdata_rx})
    `ZERO: text_num_4 = 4'h0;
    `FOUR: text_num_4 = 4'h4;
    `FIVE: text_num_4 = 4'h5;
    `NINE: text_num_4 = 4'h9;
    default: text_num_4 = 4'hF;
  endcase

  case({sliding_window[3:0], tdata_rx})
    `THREE: text_num_5 = 4'h3;
    `SEVEN: text_num_5 = 4'h7;
    `EIGHT: text_num_5 = 4'h8;
    default: text_num_5 = 4'hF;
  endcase

  assign is_number_text = (text_num_3 != 4'hF || text_num_4 != 4'hF || text_num_5 != 4'hF);

  if(text_num_3 != 4'hF) text_num = text_num_3;
  else if(text_num_4 != 4'hF) text_num = text_num_4;
  else if(text_num_5 != 4'hF) text_num = text_num_5;
end

always @(posedge clk) begin
  if(rst) begin
    state <= FIRST_DIG_SEARCH;
    acc <= '0;
    tready_rx <= 1'b0;
    first_dig <= 4'h0;
    second_dig <= 4'hF;

    tlast_tx <= 1'b0;
    tdata_tx <= '0;
    tvalid_tx <= 1'b0;

    for(integer i = 0; i < 5; i = i + 1) begin
      sliding_window[i] <= '0;
    end
  end else begin
    case (state)
      FIRST_DIG_SEARCH: begin
        tready_rx <= 1'b1;
        if(tvalid_rx) sliding_window <= {sliding_window[2:0], tdata_rx};

        if(tvalid_rx && (is_number || is_number_text)) begin
          if(is_number) begin
            first_dig <= num_shift[3:0];
          end

          if(is_number_text) begin
            first_dig <= text_num;
          end

          if(tlast_rx) begin
            state <= DO_MAC;
            tready_rx <= 1'b0;
          end
          else state <= SECOND_DIG_SEARCH;
        end
      end
      SECOND_DIG_SEARCH: begin
        tready_rx <= 1'b1;
        if(tvalid_rx) sliding_window <= {sliding_window[2:0], tdata_rx};

        if(tvalid_rx && (is_number || is_number_text)) begin
          if(is_number) begin
            second_dig <= num_shift[3:0];
          end

          if(is_number_text) begin
            second_dig <= text_num;
          end
        end

        if(tlast_rx) begin
          tready_rx <= 1'b0;
          state <= DO_MAC;
        end
      end
      DO_MAC: begin
        // tready_rx <= 1'b0;
        // reset the sliding window
        for(integer i = 0; i < 5; i = i + 1) begin
          sliding_window[i] <= '0;
        end

        if(second_dig == 4'hF) begin
          acc <= acc + (first_dig * 4'd10) + {28'd0, first_dig};
        end
        else acc <= acc + (first_dig * 4'd10) + {28'd0, second_dig};

        second_dig <= 4'hF;
        first_dig <= 4'h0;

        if(tready_tx) state <= OUTPUT_RESULT;
        else begin
          tready_rx <= 1'b1;
          state <= FIRST_DIG_SEARCH;
        end
      end
      OUTPUT_RESULT: begin
        tready_rx <= 1'b0;
        tvalid_tx <= 1'b1;
        tdata_tx <= acc;
        tlast_tx <= 1'b1;
      end
      default: state <= FIRST_DIG_SEARCH;
    endcase
  end
end



endmodule

Day_1/dut_tb.sv
`timescale 1 ps / 1 ps

`define MEM_LENGTH 21529
// `define MEM_LENGTH 93
`define PART2
// `define PART1

module dut_tb
(
    input wire clk,
    input wire rst
);

logic [$clog2(`MEM_LENGTH)-1:0] ptr;
logic [7:0] mem0 [0:`MEM_LENGTH];
logic [31:0] result [7:0];

// into DUT
logic tvalid_rx;
logic tready_rx;
logic [7:0] tdata_rx;
logic tlast_rx;

// out of DUT
logic tvalid_tx;
logic tready_tx;
logic [31:0] tdata_tx;
logic tlast_tx;

typedef enum {WRITE, READ} state_t;

state_t state;

initial begin
  $readmemh("day1.mem", mem0);
end

always @(negedge clk) begin
  if(rst) begin
    ptr <= '0;
    tvalid_rx <= 1'b0;
    tready_tx <= 1'b0;
    tdata_rx <= '0;
    tlast_rx <= 1'b0;
  end else begin
    case(state)
      WRITE: begin
        if(ptr == `MEM_LENGTH) begin
            state <= READ;
            tvalid_rx <= 1'b0;
            tready_tx <= 1'b1;
        end else begin
            tvalid_rx <= 1'b1;
            tdata_rx <= mem0[ptr];

            if(mem0[ptr+1] == 8'hFF) tlast_rx <= 1'b1;
            else tlast_rx <= 1'b0;

            if(tready_rx) begin
              if(mem0[ptr+1] == 8'hFF) ptr <= ptr + 2;
              else ptr <= ptr + 1;
            end
        end
      end
      READ: begin
        tready_tx <= 1'b1;

        result[0] <= tdata_tx;

        if(tvalid_tx) ptr <= '0;

        if(ptr == '0)
            $finish;
      end
      default: begin
        state <= WRITE;
      end
    endcase
  end
end

`ifdef PART1
day1 dut (
  .clk(clk),
  .rst(rst),

  // axis input
  .tvalid_rx(tvalid_rx),
  .tready_rx(tready_rx),
  .tdata_rx(tdata_rx),
  .tlast_rx(tlast_rx),

  // axis output
  .tvalid_tx(tvalid_tx),
  .tready_tx(tready_tx),
  .tdata_tx(tdata_tx),
  .tlast_tx(tlast_tx)
);
`endif

`ifdef PART2
day1_2 dut (
  .clk(clk),
  .rst(rst),

  // axis input
  .tvalid_rx(tvalid_rx),
  .tready_rx(tready_rx),
  .tdata_rx(tdata_rx),
  .tlast_rx(tlast_rx),

  // axis output
  .tvalid_tx(tvalid_tx),
  .tready_tx(tready_tx),
  .tdata_tx(tdata_tx),
  .tlast_tx(tlast_tx)
);
`endif



  final begin
    $writememb("result.mem", result);
  end

endmodule

Day_2/sim.vcd
$version Generated by VerilatedVcd $end
$timescale 1ps $end

 $scope module TOP $end
  $var wire  1 C clk $end
  $var wire  1 D rst $end
  $scope module dut_tb $end
   $var wire  1 C clk $end
   $var wire 15 # ptr [14:0] $end
   $var wire 32 $ result[0] [31:0] $end
   $var wire 32 % result[1] [31:0] $end
   $var wire 32 & result[2] [31:0] $end
   $var wire 32 ' result[3] [31:0] $end
   $var wire 32 ( result[4] [31:0] $end
   $var wire 32 ) result[5] [31:0] $end
   $var wire 32 * result[6] [31:0] $end
   $var wire 32 + result[7] [31:0] $end
   $var wire  1 D rst $end
   $var wire 32 0 state [31:0] $end
   $var wire  8 - tdata_rx [7:0] $end
   $var wire 32 5 tdata_tx [31:0] $end
   $var wire  1 . tlast_rx $end
   $var wire  1 6 tlast_tx $end
   $var wire  1 3 tready_rx $end
   $var wire  1 / tready_tx $end
   $var wire  1 , tvalid_rx $end
   $var wire  1 4 tvalid_tx $end
   $scope module dut $end
    $var wire 32 8 acc [31:0] $end
    $var wire  1 C clk $end
    $var wire  4 9 first_dig [3:0] $end
    $var wire  1 1 is_number $end
    $var wire  1 B is_number_text $end
    $var wire  4 2 num_shift [3:0] $end
    $var wire  1 D rst $end
    $var wire  4 : second_dig [3:0] $end
    $var wire 32 ; sliding_window [31:0] $end
    $var wire 32 7 state [31:0] $end
    $var wire  8 - tdata_rx [7:0] $end
    $var wire 32 5 tdata_tx [31:0] $end
    $var wire  4 > text_num [3:0] $end
    $var wire  4 ? text_num_3 [3:0] $end
    $var wire  4 @ text_num_4 [3:0] $end
    $var wire  4 A text_num_5 [3:0] $end
    $var wire  1 . tlast_rx $end
    $var wire  1 6 tlast_tx $end
    $var wire  1 3 tready_rx $end
    $var wire  1 / tready_tx $end
    $var wire  1 , tvalid_rx $end
    $var wire  1 4 tvalid_tx $end
    $scope module unnamedblk1 $end
     $var wire 32 < i [31:0] $end
    $upscope $end
    $scope module unnamedblk2 $end
     $var wire 32 = i [31:0] $end
    $upscope $end
   $upscope $end
  $upscope $end
 $upscope $end
$enddefinitions $end


#0
b000000000000000 #
b00000000000000000000000000000000 $
b00000000000000000000000000000000 %
b00000000000000000000000000000000 &
b00000000000000000000000000000000 '
b00000000000000000000000000000000 (
b00000000000000000000000000000000 )
b00000000000000000000000000000000 *
b00000000000000000000000000000000 +
0,
b00000000 -
0.
0/
b00000000000000000000000000000000 0
01
b0000 2
03
04
b00000000000000000000000000000000 5
06
b00000000000000000000000000000000 7
b00000000000000000000000000000000 8
b0000 9
b0000 :
b00000000000000000000000000000000 ;
b00000000000000000000000000000000 <
b00000000000000000000000000000000 =
b0000 >
b1111 ?
b1111 @
b1111 A
0B
0C
1D
#1
b1111 :
b00000000000000000000000000000101 <
1C
#2
0C
#3
1C
#4
0C
#5
13
1C
0D
#6
b000000000000001 #
1,
b00110100 -
11
b0100 2
0C
#7
b00000000000000000000000000000001 7
b0100 9
b00000000000000000000000000110100 ;
1C
#8
b000000000000010 #
b00110110 -
b0110 2
0C
#9
b0110 :
b00000000000000000011010000110110 ;
1C
#10
b000000000000011 #
b01110100 -
01
b0100 2
0C
#11
b00000000001101000011011001110100 ;
1C
#12
b000000000000100 #
b01101000 -
b1000 2
0C
#13
b00110100001101100111010001101000 ;
1C
#14
b000000000000101 #
b01110010 -
b0010 2
0C
#15
b00110110011101000110100001110010 ;
1C
#16
b000000000000110 #
b01100101 -
b0101 2
0C
#17
b01110100011010000111001001100101 ;
b0011 >
b0011 A
1B
1C
#18
b000000000000111 #
0C
#19
b0011 :
b01101000011100100110010101100101 ;
b1111 A
0B
1C
#20
b000000000001000 #
b01110110 -
b0110 2
0C
#21
b01110010011001010110010101110110 ;
1C
#22
b000000000001001 #
b01110001 -
b0001 2
0C
#23
b01100101011001010111011001110001 ;
1C
#24
b000000000001010 #
b01110011 -
b0011 2
0C
#25
b01100101011101100111000101110011 ;
1C
#26
b000000000001011 #
b00111000 -
11
b1000 2
0C
#27
b1000 :
b01110110011100010111001100111000 ;
1C
#28
b000000000001100 #
b00110001 -
b0001 2
0C
#29
b0001 :
b01110001011100110011100000110001 ;
1C
#30
b000000000001101 #
0C
#31
b01110011001110000011000100110001 ;
1C
#32
b000000000001111 #
b00110100 -
1.
b0100 2
0C
#33
03
b00000000000000000000000000000010 7
b0100 :
b00111000001100010011000100110100 ;
1C
#34
b01110100 -
0.
01
0C
#35
13
b00000000000000000000000000000000 7
b00000000000000000000000000101100 8
b0000 9
b1111 :
b00000000000000000000000000000000 ;
b00000000000000000000000000000101 =
1C
#36
b000000000010000 #
0C
#37
b00000000000000000000000001110100 ;
1C
#38
b000000000010001 #
b01101000 -
b1000 2
0C
#39
b00000000000000000111010001101000 ;
1C
#40
b000000000010010 #
b01110010 -
b0010 2
0C
#41
b00000000011101000110100001110010 ;
1C
#42
b000000000010011 #
b01100101 -
b0101 2
0C
#43
b01110100011010000111001001100101 ;
b0011 A
1B
1C
#44
b000000000010100 #
0C
#45
b00000000000000000000000000000001 7
b0011 9
b01101000011100100110010101100101 ;
b1111 A
0B
1C
#46
b000000000010101 #
b01110100 -
b0100 2
0C
#47
b01110010011001010110010101110100 ;
1C
#48
b000000000010110 #
b01110111 -
b0111 2
0C
#49
b01100101011001010111010001110111 ;
1C
#50
b000000000010111 #
b01101111 -
b1111 2
b0010 >
b0010 ?
1B
0C
#51
b0010 :
b01100101011101000111011101101111 ;
b1111 ?
0B
1C
#52
b000000000011000 #
0C
#53
b01110100011101110110111101101111 ;
1C
#54
b000000000011001 #
b01101110 -
b1110 2
0C
#55
b01110111011011110110111101101110 ;
1C
#56
b000000000011010 #
b01100101 -
b0101 2
b0001 >
b0001 ?
1B
0C
#57
b0001 :
b01101111011011110110111001100101 ;
b1111 ?
0B
1C
#58
b000000000011011 #
b01111010 -
b1010 2
0C
#59
b01101111011011100110010101111010 ;
1C
#60
b000000000011100 #
b00110001 -
11
b0001 2
0C
#61
b01101110011001010111101000110001 ;
1C
#62
b000000000011101 #
b01100111 -
01
b0111 2
0C
#63
b01100101011110100011000101100111 ;
1C
#64
b000000000011110 #
b01110100 -
b0100 2
0C
#65
b01111010001100010110011101110100 ;
1C
#66
b000000000011111 #
b01110010 -
b0010 2
0C
#67
b00110001011001110111010001110010 ;
1C
#68
b000000000100001 #
b01100100 -
1.
b0100 2
0C
#69
03
b00000000000000000000000000000010 7
b01100111011101000111001001100100 ;
1C
#70
b00110110 -
0.
11
b0110 2
0C
#71
13
b00000000000000000000000000000000 7
b00000000000000000000000001001011 8
b0000 9
b1111 :
b00000000000000000000000000000000 ;
1C
#72
b000000000100010 #
0C
#73
b00000000000000000000000000000001 7
b0110 9
b00000000000000000000000000110110 ;
1C
#74
b000000000100011 #
b01100110 -
01
0C
#75
b00000000000000000011011001100110 ;
1C
#76
b000000000100100 #
0C
#77
b00000000001101100110011001100110 ;
1C
#78
b000000000100101 #
b01111000 -
b1000 2
0C
#79
b00110110011001100110011001111000 ;
1C
#80
b000000000100110 #
b01100010 -
b0010 2
0C
#81
b01100110011001100111100001100010 ;
1C
#82
b000000000100111 #
b01110100 -
b0100 2
0C
#83
b01100110011110000110001001110100 ;
1C
#84
b000000000101000 #
b01100110 -
b0110 2
0C
#85
b01111000011000100111010001100110 ;
1C
#86
b000000000101010 #
1.
0C
#87
03
b00000000000000000000000000000010 7
b01100010011101000110011001100110 ;
1C
#88
b00110111 -
0.
11
b0111 2
0C
#89
13
b00000000000000000000000000000000 7
b00000000000000000000000010001101 8
b0000 9
b00000000000000000000000000000000 ;
1C
#90
b000000000101011 #
0C
#91
b00000000000000000000000000000001 7
b0111 9
b00000000000000000000000000110111 ;
1C
#92
b000000000101100 #
b00110110 -
b0110 2
0C
#93
b0110 :
b00000000000000000011011100110110 ;
1C
#94
b000000000101101 #
b00111001 -
b1001 2
0C
#95
b1001 :
b00000000001101110011011000111001 ;
1C
#96
b000000000101110 #
b01110100 -
01
b0100 2
0C
#97
b00110111001101100011100101110100 ;
1C
#98
b000000000101111 #
b01110111 -
b0111 2
0C
#99
b00110110001110010111010001110111 ;
1C
#100
b000000000110000 #
b01101111 -
b1111 2
b0010 >
b0010 ?
1B
0C
#101
b0010 :
b00111001011101000111011101101111 ;
b1111 ?
0B
1C
#102
b000000000110001 #
b01110100 -
b0100 2
0C
#103
b01110100011101110110111101110100 ;
1C
#104
b000000000110010 #
b01110111 -
b0111 2
0C
#105
b01110111011011110111010001110111 ;
1C
#106
b000000000110011 #
b01101111 -
b1111 2
b0010 ?
1B
0C
#107
b01101111011101000111011101101111 ;
b1111 ?
0B
1C
#108
b000000000110100 #
b00110110 -
11
b0110 2
0C
#109
b0110 :
b01110100011101110110111100110110 ;
1C
#110
b000000000110101 #
b01110010 -
01
b0010 2
0C
#111
b01110111011011110011011001110010 ;
1C
#112
b000000000110110 #
b01110110 -
b0110 2
0C
#113
b01101111001101100111001001110110 ;
1C
#114
b000000000111000 #
b00111001 -
1.
11
b1001 2
0C
#115
03
b00000000000000000000000000000010 7
b1001 :
b00110110011100100111011000111001 ;
1C
#116
b01100111 -
0.
01
b0111 2
0C
#117
13
b00000000000000000000000000000000 7
b00000000000000000000000011011100 8
b0000 9
b1111 :
b00000000000000000000000000000000 ;
1C
#118
b000000000111001 #
0C
#119
b00000000000000000000000001100111 ;
1C
#120
b000000000111010 #
b01101010 -
b1010 2
0C
#121
b00000000000000000110011101101010 ;
1C
#122
b000000000111011 #
b01110010 -
b0010 2
0C
#123
b00000000011001110110101001110010 ;
1C
#124
b000000000111100 #
b01100011 -
b0011 2
0C
#125
b01100111011010100111001001100011 ;
1C
#126
b000000000111101 #
b01101010 -
b1010 2
0C
#127
b01101010011100100110001101101010 ;
1C
#128
b000000000111110 #
b01110010 -
b0010 2
0C
#129
b01110010011000110110101001110010 ;
1C
#130
b000000000111111 #
b01101011 -
b1011 2
0C
#131
b01100011011010100111001001101011 ;
1C
#132
b000000001000000 #
b01110110 -
b0110 2
0C
#133
b01101010011100100110101101110110 ;
1C
#134
b000000001000001 #
b01100111 -
b0111 2
0C
#135
b01110010011010110111011001100111 ;
1C
#136
b000000001000010 #
b01101000 -
b1000 2
0C
#137
b01101011011101100110011101101000 ;
1C
#138
b000000001000011 #
b01110100 -
b0100 2
0C
#139
b01110110011001110110100001110100 ;
1C
#140
b000000001000100 #
b01101000 -
b1000 2
0C
#141
b01100111011010000111010001101000 ;
1C
#142
b000000001000101 #
b01110010 -
b0010 2
0C
#143
b01101000011101000110100001110010 ;
1C
#144
b000000001000110 #
b01100101 -
b0101 2
0C
#145
b01110100011010000111001001100101 ;
b0011 >
b0011 A
1B
1C
#146
b000000001000111 #
0C
#147
b00000000000000000000000000000001 7
b0011 9
b01101000011100100110010101100101 ;
b1111 A
0B
1C
#148
b000000001001000 #
b01100111 -
b0111 2
0C
#149
b01110010011001010110010101100111 ;
1C
#150
b000000001001001 #
b01110001 -
b0001 2
0C
#151
b01100101011001010110011101110001 ;
1C
#152
b000000001001010 #
0C
#153
b01100101011001110111000101110001 ;
1C
#154
b000000001001011 #
b01110010 -
b0010 2
0C
#155
b01100111011100010111000101110010 ;
1C
#156
b000000001001100 #
b01100111 -
b0111 2
0C
#157
b01110001011100010111001001100111 ;
1C
#158
b000000001001101 #
b00111000 -
11
b1000 2
0C
#159
b1000 :
b01110001011100100110011100111000 ;
1C
#160
b000000001001110 #
b00110010 -
b0010 2
0C
#161
b0010 :
b01110010011001110011100000110010 ;
1C
#162
b000000001001111 #
b01110001 -
01
b0001 2
0C
#163
b01100111001110000011001001110001 ;
1C
#164
b000000001010000 #
b01100010 -
b0010 2
0C
#165
b00111000001100100111000101100010 ;
1C
#166
b000000001010001 #
b01100011 -
b0011 2
0C
#167
b00110010011100010110001001100011 ;
1C
#168
b000000001010011 #
b01110100 -
1.
b0100 2
0C
#169
03
b00000000000000000000000000000010 7
b01110001011000100110001101110100 ;
1C
#170
b01111010 -
0.
b1010 2
0C
#171
13
b00000000000000000000000000000000 7
b00000000000000000000000011111100 8
b0000 9
b1111 :
b00000000000000000000000000000000 ;
1C
#172
b000000001010100 #
0C
#173
b00000000000000000000000001111010 ;
1C
#174
b000000001010101 #
b01101011 -
b1011 2
0C
#175
b00000000000000000111101001101011 ;
1C
#176
b000000001010110 #
b01111000 -
b1000 2
0C
#177
b00000000011110100110101101111000 ;
1C
#178
b000000001010111 #
b01101010 -
b1010 2
0C
#179
b01111010011010110111100001101010 ;
1C
#180
b000000001011000 #
b01101000 -
b1000 2
0C
#181
b01101011011110000110101001101000 ;
1C
#182
b000000001011001 #
b01100111 -
b0111 2
0C
#183
b01111000011010100110100001100111 ;
1C
#184
b000000001011010 #
b01110000 -
b0000 2
0C
#185
b01101010011010000110011101110000 ;
1C
#186
b000000001011011 #
b01110010 -
b0010 2
0C
#187
b01101000011001110111000001110010 ;
1C
#188
b000000001011100 #
b01110100 -
b0100 2
0C
#189
b01100111011100000111001001110100 ;
1C
#190
b000000001011101 #
b01110010 -
b0010 2
0C
#191
b01110000011100100111010001110010 ;
1C
#192
b000000001011110 #
b01101100 -
b1100 2
0C
#193
b01110010011101000111001001101100 ;
1C
#194
b000000001011111 #
b01100011 -
b0011 2
0C
#195
b01110100011100100110110001100011 ;
1C
#196
b000000001100000 #
b01100110 -
b0110 2
0C
#197
b01110010011011000110001101100110 ;
1C
#198
b000000001100001 #
b01100101 -
b0101 2
0C
#199
b01101100011000110110011001100101 ;
1C
#200
b000000001100010 #
b01101001 -
b1001 2
0C
#201
b01100011011001100110010101101001 ;
1C
#202
b000000001100011 #
b01100111 -
b0111 2
0C
#203
b01100110011001010110100101100111 ;
1C
#204
b000000001100100 #
b01101000 -
b1000 2
0C
#205
b01100101011010010110011101101000 ;
1C
#206
b000000001100101 #
b01110100 -
b0100 2
b1000 >
b1000 A
1B
0C
#207
b00000000000000000000000000000001 7
b1000 9
b01101001011001110110100001110100 ;
b1111 A
0B
1C
#208
b000000001100110 #
b00110111 -
11
b0111 2
0C
#209
b0111 :
b01100111011010000111010000110111 ;
1C
#210
b000000001100111 #
b00111001 -
b1001 2
0C
#211
b1001 :
b01101000011101000011011100111001 ;
1C
#212
b000000001101000 #
b00110101 -
b0101 2
0C
#213
b0101 :
b01110100001101110011100100110101 ;
1C
#214
b000000001101001 #
b01100110 -
01
b0110 2
0C
#215
b00110111001110010011010101100110 ;
1C
#216
b000000001101010 #
b01101001 -
b1001 2
0C
#217
b00111001001101010110011001101001 ;
1C
#218
b000000001101011 #
b01110110 -
b0110 2
0C
#219
b00110101011001100110100101110110 ;
1C
#220
b000000001101100 #
b01100101 -
b0101 2
b0101 >
b0101 @
1B
0C
#221
b01100110011010010111011001100101 ;
b1111 @
0B
1C
#222
b000000001101110 #
b00111000 -
1.
11
b1000 2
0C
#223
03
b00000000000000000000000000000010 7
b1000 :
b01101001011101100110010100111000 ;
1C
#224
b00111001 -
0.
b1001 2
0C
#225
13
b00000000000000000000000000000000 7
b00000000000000000000000101010100 8
b0000 9
b1111 :
b00000000000000000000000000000000 ;
1C
#226
b000000001101111 #
0C
#227
b00000000000000000000000000000001 7
b1001 9
b00000000000000000000000000111001 ;
1C
#228
b000000001110000 #
0C
#229
b1001 :
b00000000000000000011100100111001 ;
1C
#230
b000000001110001 #
b01110011 -
01
b0011 2
0C
#231
b00000000001110010011100101110011 ;
1C
#232
b000000001110010 #
b01100101 -
b0101 2
0C
#233
b00111001001110010111001101100101 ;
1C
#234
b000000001110011 #
b01110110 -
b0110 2
0C
#235
b00111001011100110110010101110110 ;
1C
#236
b000000001110100 #
b01100101 -
b0101 2
0C
#237
b01110011011001010111011001100101 ;
1C
#238
b000000001110101 #
b01101110 -
b1110 2
b0111 >
b0111 A
1B
0C
#239
b0111 :
b01100101011101100110010101101110 ;
b1111 A
0B
1C
#240
b000000001110110 #
b00110011 -
11
b0011 2
0C
#241
b0011 :
b01110110011001010110111000110011 ;
1C
#242
b000000001110111 #
b01110110 -
01
b0110 2
0C
#243
b01100101011011100011001101110110 ;
1C
#244
b000000001111000 #
b01100100 -
b0100 2
0C
#245
b01101110001100110111011001100100 ;
1C
#246
b000000001111001 #
b01100011 -
b0011 2
0C
#247
b00110011011101100110010001100011 ;
1C
#248
b000000001111010 #
b01100111 -
b0111 2
0C
#249
b01110110011001000110001101100111 ;
1C
#250
b000000001111011 #
b01110110 -
b0110 2
0C
#251
b01100100011000110110011101110110 ;
1C
#252
b000000001111100 #
b01101101 -
b1101 2
0C
#253
b01100011011001110111011001101101 ;
1C
#254
b000000001111101 #
b01110110 -
b0110 2
0C
#255
b01100111011101100110110101110110 ;
1C
#256
b000000001111110 #
b01111000 -
b1000 2
0C
#257
b01110110011011010111011001111000 ;
1C
#258
b000000001111111 #
b01110100 -
b0100 2
0C
#259
b01101101011101100111100001110100 ;
1C
#260
b000000010000000 #
b01101010 -
b1010 2
0C
#261
b01110110011110000111010001101010 ;
1C
#262
b000000010000001 #
b01110100 -
b0100 2
0C
#263
b01111000011101000110101001110100 ;
1C
#264
b000000010000010 #
b01110111 -
b0111 2
0C
#265
b01110100011010100111010001110111 ;
1C
#266
b000000010000011 #
b01101111 -
b1111 2
b0010 >
b0010 ?
1B
0C
#267
b0010 :
b01101010011101000111011101101111 ;
b1111 ?
0B
1C
#268
b000000010000100 #
b01100100 -
b0100 2
0C
#269
b01110100011101110110111101100100 ;
1C
#270
b000000010000101 #
b01100011 -
b0011 2
0C
#271
b01110111011011110110010001100011 ;
1C
#272
b000000010000111 #
b00110101 -
1.
11
b0101 2
0C
#273
03
b00000000000000000000000000000010 7
b0101 :
b01101111011001000110001100110101 ;
1C
#274
b01110100 -
0.
01
b0100 2
0C
#275
13
b00000000000000000000000000000000 7
b00000000000000000000000110110011 8
b0000 9
b1111 :
b00000000000000000000000000000000 ;
1C
#276
b000000010001000 #
0C
#277
b00000000000000000000000001110100 ;
1C
#278
b000000010001001 #
b01101000 -
b1000 2
0C
#279
b00000000000000000111010001101000 ;
1C
#280
b000000010001010 #
b01110010 -
b0010 2
0C
#281
b00000000011101000110100001110010 ;
1C
#282
b000000010001011 #
b01100101 -
b0101 2
0C
#283
b01110100011010000111001001100101 ;
b0011 >
b0011 A
1B
1C
#284
b000000010001100 #
0C
#285
b00000000000000000000000000000001 7
b0011 9
b01101000011100100110010101100101 ;
b1111 A
0B
1C
#286
b000000010001101 #
b00110101 -
11
0C
#287
b0101 :
b01110010011001010110010100110101 ;
1C
#288
b000000010001110 #
b01100101 -
01
0C
#289
b01100101011001010011010101100101 ;
1C
#290
b000000010001111 #
b01101001 -
b1001 2
0C
#291
b01100101001101010110010101101001 ;
1C
#292
b000000010010000 #
b01100111 -
b0111 2
0C
#293
b00110101011001010110100101100111 ;
1C
#294
b000000010010001 #
b01101000 -
b1000 2
0C
#295
b01100101011010010110011101101000 ;
1C
#296
b000000010010010 #
b01110100 -
b0100 2
b1000 >
b1000 A
1B
0C
#297
b1000 :
b01101001011001110110100001110100 ;
b1111 A
0B
1C
#298
b000000010010011 #
0C
#299
b01100111011010000111010001110100 ;
1C
#300
b000000010010100 #
b01101000 -
b1000 2
0C
#301
b01101000011101000111010001101000 ;
1C
#302
b000000010010101 #
b01110010 -
b0010 2
0C
#303
b01110100011101000110100001110010 ;
1C
#304
b000000010010110 #
b01100101 -
b0101 2
0C
#305
b01110100011010000111001001100101 ;
b0011 >
b0011 A
1B
1C
#306
b000000010010111 #
0C
#307
b0011 :
b01101000011100100110010101100101 ;
b1111 A
0B
1C
#308
b000000010011000 #
b00110011 -
11
b0011 2
0C
#309
b01110010011001010110010100110011 ;
1C
#310
b000000010011001 #
b01100110 -
01
b0110 2
0C
#311
b01100101011001010011001101100110 ;
1C
#312
b000000010011010 #
b01101111 -
b1111 2
0C
#313
b01100101001100110110011001101111 ;
1C
#314
b000000010011011 #
b01110101 -
b0101 2
0C
#315
b00110011011001100110111101110101 ;
1C
#316
b000000010011100 #
b01110010 -
b0010 2
b0100 >
b0100 @
1B
0C
#317
b0100 :
b01100110011011110111010101110010 ;
b1111 @
0B
1C
#318
b000000010011101 #
b00110011 -
11
b0011 2
0C
#319
b0011 :
b01101111011101010111001000110011 ;
1C
#320
b000000010011110 #
b01110110 -
01
b0110 2
0C
#321
b01110101011100100011001101110110 ;
1C
#322
b000000010011111 #
b01110100 -
b0100 2
0C
#323
b01110010001100110111011001110100 ;
1C
#324
b000000010100000 #
b01101011 -
b1011 2
0C
#325
b00110011011101100111010001101011 ;
1C
#326
b000000010100001 #
0C
#327
b01110110011101000110101101101011 ;
1C
#328
b000000010100010 #
b01110001 -
b0001 2
0C
#329
b01110100011010110110101101110001 ;
1C
#330
b000000010100011 #
b01110010 -
b0010 2
0C
#331
b01101011011010110111000101110010 ;
1C
#332
b000000010100100 #
b01100111 -
b0111 2
0C
#333
b01101011011100010111001001100111 ;
1C
#334
b000000010100101 #
b01111000 -
b1000 2
0C
#335
b01110001011100100110011101111000 ;
1C
#336
b000000010100111 #
b01110011 -
1.
b0011 2
0C
#337
03
b00000000000000000000000000000010 7
b01110010011001110111100001110011 ;
1C
#338
b01100110 -
0.
b0110 2
0C
#339
13
b00000000000000000000000000000000 7
b00000000000000000000000111010100 8
b0000 9
b1111 :
b00000000000000000000000000000000 ;
1C
#340
b000000010101000 #
0C
#341
b00000000000000000000000001100110 ;
1C
#342
b000000010101001 #
b01101111 -
b1111 2
0C
#343
b00000000000000000110011001101111 ;
1C
#344
b000000010101010 #
b01110101 -
b0101 2
0C
#345
b00000000011001100110111101110101 ;
1C
#346
b000000010101011 #
b01110010 -
b0010 2
b0100 @
1B
0C
#347
b00000000000000000000000000000001 7
b0100 9
b01100110011011110111010101110010 ;
b1111 @
0B
1C
#348
b000000010101100 #
b00111000 -
11
b1000 2
0C
#349
b1000 :
b01101111011101010111001000111000 ;
1C
#350
b000000010101101 #
b00110110 -
b0110 2
0C
#351
b0110 :
b01110101011100100011100000110110 ;
1C
#352
b000000010101110 #
b00110011 -
b0011 2
0C
#353
b0011 :
b01110010001110000011011000110011 ;
1C
#354
b000000010101111 #
b01101101 -
01
b1101 2
0C
#355
b00111000001101100011001101101101 ;
1C
#356
b000000010110000 #
b01110010 -
b0010 2
0C
#357
b00110110001100110110110101110010 ;
1C
#358
b000000010110001 #
0C
#359
b00110011011011010111001001110010 ;
1C
#360
b000000010110010 #
b01101110 -
b1110 2
0C
#361
b01101101011100100111001001101110 ;
1C
#362
b000000010110011 #
b01110010 -
b0010 2
0C
#363
b01110010011100100110111001110010 ;
1C
#364
b000000010110100 #
b01110011 -
b0011 2
0C
#365
b01110010011011100111001001110011 ;
1C
#366
b000000010110101 #
b01111000 -
b1000 2
0C
